Workbook

Sheet Tổng quan hệ thống
A1: BÁO CÁO TỔNG QUAN HỆ THỐNG TIỀN GIÁM ĐỊNH XML3176
A2: Kỳ báo cáo: hồ sơ BHYT ra viện 01/10–15/10/2026 tại cơ sở 01929 và 37470 (dữ liệu nạp lại ngày 16/10/2026). Số liệu chốt ngày 16/10/2026 từ CSDL thật (truy vấn chỉ đọc); bộ kiểm commit 63e21fa8. Các ô tính từ sheet khác là công thức, tự cập nhật khi sheet nguồn thay đổi.
A4: 1. Hệ thống Tiền giám định làm gì
A5: • Mục đích: kiểm tra hồ sơ XML theo Quyết định 3176/QĐ-BYT TRƯỚC khi gửi cổng giám định BHXH, phát hiện sai sót để sửa tại nguồn (HIS, PACS/LIS, danh mục, khoa/phòng), giảm hồ sơ bị BHXH từ chối hoặc xuất toán.
A6: • Luồng xử lý: (1) Nạp XML từ HIS → (2) Kiểm tự động từng hồ sơ: 12 bảng XML và kiểm tổng thể toàn hồ sơ (XMLComplete) → (3) Có lỗi CHẶN GỬI: hồ sơ dừng, đơn vị sửa rồi nạp lại; chỉ có CẢNH BÁO: hồ sơ đi tiếp → (4) Xuất XML, ký số → (5) Gửi cổng giám định BHXH.
A7: • Nguyên tắc: không tự sửa dữ liệu trên bản gửi cổng (khác hệ thống FIXERROR – xem sheet "Đối chiếu FIXERROR"); mỗi mã lỗi gán một đơn vị chủ trì và đơn vị phối hợp để giao việc (sheet "Danh mục lỗi").
A9: 2. Quy mô dữ liệu và danh mục
A10: Chỉ tiêu | B10: Giá trị | C10: Ghi chú
A11: Hồ sơ trong kỳ | B11: 23967 | C11: Cơ sở 01929: 18.845; cơ sở 37470: 5.122
A12: Dòng chi tiết được kiểm | B12: 3816571 | C12: Thuốc XML2: 560.375; DVKT/VTYT XML3: 955.173; cận lâm sàng XML4: 2.091.705; diễn biến XML5: 209.318
A13: Chi phí BHYT thanh toán (T_BHTT, tỷ đồng) | B13: 216.33 | C13: Tổng T_BHTT trên XML1 của các hồ sơ trong kỳ
A14: Mã lỗi trong danh mục | B14: 252 | C14: Đang kiểm 215 mã, trong đó 137 mã chặn gửi; còn lại đã tắt hoặc đã gộp vào mã mới
A15: Mã lỗi phát sinh trong kỳ | B15: =COUNTIF('Danh mục lỗi'!$G$5:$G$222,">0") -> 116 | C15: Đếm từ sheet "Danh mục lỗi"
A16: Danh mục DVKT | B16: 24318 | C16: Cơ sở 01929: 8.595; cơ sở 37470: 15.723
A17: Danh mục thuốc | B17: 8689
A18: Danh mục VTYT | B18: 5243
A19: Danh mục nhân viên y tế (NVYT) | B19: 5089
A20: Danh mục trang thiết bị (mã máy) | B20: 8298
A21: DVKT bắt buộc có mã máy | B21: 3471 | C21: Căn cứ quy tắc thiếu mã máy từ 16/10/2026
A22: Cặp vật phẩm kèm DVKT | B22: 756 | C22: Thuốc/VTYT phải kèm đúng DVKT mẹ (quy tắc R1/R2)
A23: DVKT bắt buộc kèm vật phẩm | B23: 37 | C23: Quy tắc R3
A24: Danh mục cơ sở KCB | B24: 13843
A25: Danh mục ICD-10 | B25: 17075
A26: Tốc độ kiểm | B26: ≈ 0,36 giây/hồ sơ | C26: Đo trên 200 hồ sơ mẫu ngày 15/10/2026; mỗi hồ sơ một lượt kiểm; sửa danh mục có hiệu lực ngay, không cần khởi động lại
A28: 3. Kết quả kiểm trong kỳ
A29: Trạng thái hồ sơ | B29: Số hồ sơ | C29: % hồ sơ | D29: T_BHTT (tỷ đồng) | E29: % T_BHTT | F29: Ý nghĩa
A30: Tổng hồ sơ | B30: 23967 | C30: 1 | D30: 216.33 | E30: 1
A31: Không có lỗi | B31: 1995 | C31: =B31/$B$30 -> 0.083239454 | D31: 3.44 | E31: =D31/$D$30 -> 0.015901632 | F31: Đạt hoàn toàn
A32: Chỉ có cảnh báo | B32: 10432 | C32: =B32/$B$30 -> 0.43526516 | D32: 37.44 | E32: =D32/$D$30 -> 0.17306892 | F32: Được xuất, ký, gửi nhưng có nguy cơ BHXH giảm trừ
A33: Bị chặn gửi (≥ 1 lỗi chặn) | B33: 11540 | C33: =B33/$B$30 -> 0.48149539 | D33: 175.45 | E33: =D33/$D$30 -> 0.81102945 | F33: Không được xuất/ký/gửi đến khi sửa và nạp lại
A34: Đã xuất XML | B34: 12424 | C34: =B34/$B$30 -> 0.51837944 | D34: Khớp số hồ sơ không bị chặn
A35: Đã ký số | B35: 12429 | C35: =B35/$B$30 -> 0.51858806
A36: Đã gửi cổng qua Tiền giám định | B36: 0 | C36: =B36/$B$30 -> 0 | D36: Chưa gửi hồ sơ nào của kỳ này; lần gửi cổng gần nhất qua Tiền giám định là 29/09/2026
A38: 4. Theo cơ sở KCB
A39: Cơ sở | B39: Số hồ sơ | C39: Bị chặn | D39: % bị chặn | E39: Không lỗi | F39: T_BHTT (tỷ đồng) | G39: T_BHTT hồ sơ bị chặn (tỷ đồng)
A40: Cơ sở 01929 | B40: 18845 | C40: 9547 | D40: =C40/B40 -> 0.50660653 | E40: 1585 | F40: 174.4 | G40: 143.96
A41: Cơ sở 37470 | B41: 5122 | C41: 1993 | D41: =C41/B41 -> 0.38910582 | E41: 410 | F41: 41.93 | G41: 31.48
A42: Cộng | B42: =SUM(B40:B41) -> 23967 | C42: =SUM(C40:C41) -> 11540 | D42: =C42/B42 -> 0.48149539 | E42: =SUM(E40:E41) -> 1995 | F42: =SUM(F40:F41) -> 216.33 | G42: =SUM(G40:G41) -> 175.44
A44: 5. Theo loại khám chữa bệnh (MA_LOAI_KCB)
A45: Loại KCB | B45: Số hồ sơ | C45: Bị chặn | D45: % bị chặn | E45: Không lỗi | F45: T_BHTT (tỷ đồng) | G45: T_BHTT hồ sơ bị chặn (tỷ đồng)
A46: 01 – Khám bệnh | B46: 10902 | C46: 2578 | D46: =C46/B46 -> 0.23647037 | E46: 1957 | F46: 27.02 | G46: 7.7
A47: 02 – Điều trị ngoại trú | B47: 1285 | C47: 910 | D47: =C47/B47 -> 0.70817121 | E47: 2 | F47: 8 | G47: 5.41
A48: 03 – Điều trị nội trú | B48: 11271 | C48: 7773 | D48: =C48/B48 -> 0.68964599 | E48: 19 | F48: 178.6 | G48: 160.04
A49: 04 – Điều trị nội trú ban ngày | B49: 124 | C49: 111 | D49: =C49/B49 -> 0.89516129 | E49: 0 | F49: 2.24 | G49: 2.11
A50: Mã 08 | B50: 12 | C50: 10 | D50: =C50/B50 -> 0.83333333 | E50: 0 | F50: 0.06 | G50: 0.04
A51: 09 – Điều trị nội trú dưới 4 giờ | B51: 373 | C51: 158 | D51: =C51/B51 -> 0.42359249 | E51: 17 | F51: 0.41 | G51: 0.16
A52: Cộng | B52: =SUM(B46:B51) -> 23967 | C52: =SUM(C46:C51) -> 11540 | D52: =C52/B52 -> 0.48149539 | E52: =SUM(E46:E51) -> 1995 | F52: =SUM(F46:F51) -> 216.33 | G52: =SUM(G46:G51) -> 175.46
A54: 6. Theo bảng XML
A55: Bảng | B55: Mã lỗi đang kiểm | C55: Trong đó chặn gửi | D55: Hồ sơ có lỗi | E55: % hồ sơ | F55: Nội dung bảng
A56: XML1 | B56: 48 | C56: 39 | D56: 945 | E56: =D56/$B$30 -> 0.039429215 | F56: Thông tin tổng hợp hồ sơ, hành chính, chi phí
A57: XML2 | B57: 25 | C57: 8 | D57: 11240 | E57: =D57/$B$30 -> 0.46897818 | F57: Thuốc
A58: XML3 | B58: 56 | C58: 24 | D58: 20450 | E58: =D58/$B$30 -> 0.85325656 | F58: Dịch vụ kỹ thuật và vật tư y tế
A59: XML4 | B59: 8 | C59: 6 | D59: 18242 | E59: =D59/$B$30 -> 0.76112989 | F59: Kết quả cận lâm sàng
A60: XML5 | B60: 2 | C60: 1 | D60: 1584 | E60: =D60/$B$30 -> 0.066090875 | F60: Diễn biến lâm sàng
A61: XML7 | B61: 3 | C61: 3 | D61: 643 | E61: =D61/$B$30 -> 0.026828556 | F61: Giấy ra viện
A62: XML8 | B62: 4 | C62: 3 | D62: 7283 | E62: =D62/$B$30 -> 0.30387616 | F62: Tóm tắt hồ sơ bệnh án
A63: XML9 | B63: 6 | C63: 6 | D63: 10 | E63: =D63/$B$30 -> 0.00041724037 | F63: Giấy chứng sinh
A64: XML11 | B64: 13 | C64: 13 | D64: 26 | E64: =D64/$B$30 -> 0.001084825 | F64: Giấy chứng nhận nghỉ việc hưởng BHXH
A65: XML13 | B65: 14 | C65: 14 | D65: 3 | E65: =D65/$B$30 -> 0.00012517211 | F65: Giấy chuyển tuyến
A66: XML14 | B66: 4 | C66: 4 | D66: 362 | E66: =D66/$B$30 -> 0.015104101 | F66: Giấy hẹn khám lại
A67: XMLComplete | B67: 32 | C67: 16 | D67: 13232 | E67: =D67/$B$30 -> 0.55209246 | F67: Kiểm tổng thể: đối chiếu chéo giữa các bảng, NVYT, ngày giường, mức hưởng, vật phẩm kèm DVKT
A69: 7. Theo đơn vị chủ trì xử lý (tự lấy từ sheet "Tổng hợp")
A70: Đơn vị chủ trì | B70: Số mã lỗi phát sinh | C70: Trong đó chặn gửi | D70: Lượt hồ sơ-lỗi | E70: Lượt hồ sơ-lỗi chặn gửi | F70: Mã lỗi lớn nhất
A71: ='Tổng hợp'!A6 -> Phòng BHYT | B71: ='Tổng hợp'!B6 -> 32 | C71: ='Tổng hợp'!C6 -> 21 | D71: ='Tổng hợp'!D6 -> 12127 | E71: ='Tổng hợp'!E6 -> 1177 | F71: =IF('Tổng hợp'!F6="","",'Tổng hợp'!F6) -> XML3_OVERLAPPING_BED_USAGE (8.117 HS)
A72: ='Tổng hợp'!A7 -> CNTT | B72: ='Tổng hợp'!B7 -> 23 | C72: ='Tổng hợp'!C7 -> 9 | D72: ='Tổng hợp'!D7 -> 62282 | E72: ='Tổng hợp'!E7 -> 10107 | F72: =IF('Tổng hợp'!F7="","",'Tổng hợp'!F7) -> XML4_CHI_SO_EMPTY (17.415 HS)
A73: ='Tổng hợp'!A8 -> Khoa Dược | B73: ='Tổng hợp'!B8 -> 8 | C73: ='Tổng hợp'!C8 -> 1 | D73: ='Tổng hợp'!D8 -> 17221 | E73: ='Tổng hợp'!E8 -> 396 | F73: =IF('Tổng hợp'!F8="","",'Tổng hợp'!F8) -> XML2_INVALID_DANG_BAO_CHE (7.033 HS)
A74: ='Tổng hợp'!A9 -> Phòng VT-TBYT | B74: ='Tổng hợp'!B9 -> 6 | C74: ='Tổng hợp'!C9 -> 2 | D74: ='Tổng hợp'!D9 -> 19568 | E74: ='Tổng hợp'!E9 -> 32 | F74: =IF('Tổng hợp'!F9="","",'Tổng hợp'!F9) -> XML3_INFO_ERROR_MA_MAY_NOT_FOUND (18.854 HS)
A75: ='Tổng hợp'!A10 -> Phòng KHTH | B75: ='Tổng hợp'!B10 -> 4 | C75: ='Tổng hợp'!C10 -> 4 | D75: ='Tổng hợp'!D10 -> 15601 | E75: ='Tổng hợp'!E10 -> 15601 | F75: =IF('Tổng hợp'!F10="","",'Tổng hợp'!F10) -> XML3_INVALID_MA_DICH_VU (7.344 HS)
A76: ='Tổng hợp'!A11 -> Phòng TCKT | B76: ='Tổng hợp'!B11 -> 1 | C76: ='Tổng hợp'!C11 -> 0 | D76: ='Tổng hợp'!D11 -> 232 | E76: ='Tổng hợp'!E11 -> 0 | F76: =IF('Tổng hợp'!F11="","",'Tổng hợp'!F11) -> XML3_INVALID_APPROVED_DON_GIA_BH (232 HS)
A77: ='Tổng hợp'!A12 -> Phòng TCCB | B77: ='Tổng hợp'!B12 -> 1 | C77: ='Tổng hợp'!C12 -> 0 | D77: ='Tổng hợp'!D12 -> 10455 | E77: ='Tổng hợp'!E12 -> 0 | F77: =IF('Tổng hợp'!F12="","",'Tổng hợp'!F12) -> XMLComplete_NVYT_KHONG_CO_TRONG_DM (10.455 HS)
A78: ='Tổng hợp'!A13 -> Khoa lâm sàng | B78: ='Tổng hợp'!B13 -> 33 | C78: ='Tổng hợp'!C13 -> 25 | D78: ='Tổng hợp'!D13 -> 19204 | E78: ='Tổng hợp'!E13 -> 2232 | F78: =IF('Tổng hợp'!F13="","",'Tổng hợp'!F13) -> XML8_TOMTAT_KQ_TOO_SHORT (7.258 HS)
A79: ='Tổng hợp'!A14 -> Tiếp đón | B79: ='Tổng hợp'!B14 -> 8 | C79: ='Tổng hợp'!C14 -> 4 | D79: ='Tổng hợp'!D14 -> 451 | E79: ='Tổng hợp'!E14 -> 19 | F79: =IF('Tổng hợp'!F14="","",'Tổng hợp'!F14) -> XML1_ADMIN_INFO_ERROR_SO_CCCD (420 HS)
A80: ='Tổng hợp'!A15 -> Đơn vị PM Tiền giám định | B80: ='Tổng hợp'!B15 -> 0 | C80: ='Tổng hợp'!C15 -> 0 | D80: ='Tổng hợp'!D15 -> 0 | E80: ='Tổng hợp'!E15 -> 0 | F80: =IF('Tổng hợp'!F15="","",'Tổng hợp'!F15) -> (không còn lỗi)
A81: ='Tổng hợp'!A16 -> Tổng | B81: ='Tổng hợp'!B16 -> 116 | C81: ='Tổng hợp'!C16 -> 66 | D81: ='Tổng hợp'!D16 -> 157141 | E81: ='Tổng hợp'!E16 -> 29564 | F81: =IF('Tổng hợp'!F16="","",'Tổng hợp'!F16)
A82: "Lượt hồ sơ-lỗi" cộng số hồ sơ của từng mã, một hồ sơ nhiều lỗi được đếm nhiều lần – dùng để so sánh khối lượng việc giữa các đơn vị.
A84: 8. Mười lỗi CHẶN GỬI nhiều hồ sơ nhất
A85: Mã lỗi | B85: Số hồ sơ | C85: % hồ sơ | D85: Đơn vị chủ trì | E85: Tên lỗi
A86: ='Danh mục lỗi'!B10 -> XML3_INVALID_MA_DICH_VU | B86: ='Danh mục lỗi'!G10 -> 7344 | C86: ='Danh mục lỗi'!G10/$B$30 -> 0.30642133 | D86: ='Danh mục lỗi'!L10 -> Phòng KHTH | E86: ='Danh mục lỗi'!D10 -> Mã dịch vụ không tồn tại
A87: ='Danh mục lỗi'!B11 -> XML4_INFO_ERROR_MA_DICH_VU_NOT_FOUND | B87: ='Danh mục lỗi'!G11 -> 7332 | C87: ='Danh mục lỗi'!G11/$B$30 -> 0.30592064 | D87: ='Danh mục lỗi'!L11 -> Phòng KHTH | E87: ='Danh mục lỗi'!D11 -> Mã dịch vụ không tồn tại
A88: ='Danh mục lỗi'!B19 -> XML4_XN_MISSING_VALUE_RESULT | B88: ='Danh mục lỗi'!G19 -> 3753 | C88: ='Danh mục lỗi'!G19/$B$30 -> 0.15659031 | D88: ='Danh mục lỗi'!L19 -> CNTT | E88: ='Danh mục lỗi'!D19 -> Xét nghiệm không nhập giá trị và kết quả
A89: ='Danh mục lỗi'!B20 -> XMLComplete_NVYT_THIEU | B89: ='Danh mục lỗi'!G20 -> 3533 | C89: ='Danh mục lỗi'!G20/$B$30 -> 0.14741102 | D89: ='Danh mục lỗi'!L20 -> CNTT | E89: ='Danh mục lỗi'!D20 -> Thiếu mã nhân viên y tế
A90: ='Danh mục lỗi'!B30 -> XML4_INFO_ERROR_NGAY_KQ | B90: ='Danh mục lỗi'!G30 -> 1271 | C90: ='Danh mục lỗi'!G30/$B$30 -> 0.053031251 | D90: ='Danh mục lỗi'!L30 -> CNTT | E90: ='Danh mục lỗi'!D30 -> Thiếu ngày trả kết quả
A91: ='Danh mục lỗi'!B32 -> XML4_INFO_ERROR_GIA_TRI_LENGTH | B91: ='Danh mục lỗi'!G32 -> 1091 | C91: ='Danh mục lỗi'!G32/$B$30 -> 0.045520925 | D91: ='Danh mục lỗi'!L32 -> CNTT | E91: ='Danh mục lỗi'!D32 -> Giá trị quá dài
A92: ='Danh mục lỗi'!B34 -> XML3_INVALID_TEN_DICH_VU | B92: ='Danh mục lỗi'!G34 -> 858 | C92: ='Danh mục lỗi'!G34/$B$30 -> 0.035799224 | D92: ='Danh mục lỗi'!L34 -> Phòng KHTH | E92: ='Danh mục lỗi'!D34 -> Tên dịch vụ kỹ thuật khác tên được phê duyệt
A93: ='Danh mục lỗi'!B36 -> XML7_INFO_ERROR_PP_DIEUTRI | B93: ='Danh mục lỗi'!G36 -> 642 | C93: ='Danh mục lỗi'!G36/$B$30 -> 0.026786832 | D93: ='Danh mục lỗi'!L36 -> Khoa lâm sàng | E93: ='Danh mục lỗi'!D36 -> Thiếu phương pháp điều trị
A94: ='Danh mục lỗi'!B37 -> XML8_INFO_ERROR_PP_DIEUTRI | B94: ='Danh mục lỗi'!G37 -> 636 | C94: ='Danh mục lỗi'!G37/$B$30 -> 0.026536488 | D94: ='Danh mục lỗi'!L37 -> Khoa lâm sàng | E94: ='Danh mục lỗi'!D37 -> Thiếu phương pháp điều trị
A95: ='Danh mục lỗi'!B39 -> XMLComplete_MUC_HUONG_EXCEEDS_ENTITLEMENT | B95: ='Danh mục lỗi'!G39 -> 514 | C95: ='Danh mục lỗi'!G39/$B$30 -> 0.021446155 | D95: ='Danh mục lỗi'!L39 -> Phòng BHYT | E95: ='Danh mục lỗi'!D39 -> Mức hưởng khai vượt trần cho phép
A97: 9. Mười lỗi CẢNH BÁO nhiều hồ sơ nhất
A98: Mã lỗi | B98: Số hồ sơ | C98: % hồ sơ | D98: Đơn vị chủ trì | E98: Tên lỗi
A99: ='Danh mục lỗi'!B5 -> XML3_INFO_ERROR_MA_MAY_NOT_FOUND | B99: ='Danh mục lỗi'!G5 -> 18854 | C99: ='Danh mục lỗi'!G5/$B$30 -> 0.786665 | D99: ='Danh mục lỗi'!L5 -> Phòng VT-TBYT | E99: ='Danh mục lỗi'!D5 -> Mã máy không tồn tại trong danh mục trang thiết bị
A100: ='Danh mục lỗi'!B6 -> XML4_CHI_SO_EMPTY | B100: ='Danh mục lỗi'!G6 -> 17415 | C100: ='Danh mục lỗi'!G6/$B$30 -> 0.72662411 | D100: ='Danh mục lỗi'!L6 -> CNTT | E100: ='Danh mục lỗi'!D6 -> Mã/tên chỉ số để trống
A101: ='Danh mục lỗi'!B7 -> XMLComplete_NVYT_KHONG_CO_TRONG_DM | B101: ='Danh mục lỗi'!G7 -> 10455 | C101: ='Danh mục lỗi'!G7/$B$30 -> 0.43622481 | D101: ='Danh mục lỗi'!L7 -> Phòng TCCB | E101: ='Danh mục lỗi'!D7 -> Mã nhân viên y tế không có trong danh mục NVYT
A102: ='Danh mục lỗi'!B8 -> XML3_INFO_ERROR_GROUP_CODE_MA_MAY | B102: ='Danh mục lỗi'!G8 -> 9985 | C102: ='Danh mục lỗi'!G8/$B$30 -> 0.41661451 | D102: ='Danh mục lỗi'!L8 -> CNTT | E102: ='Danh mục lỗi'!D8 -> Thiếu mã máy
A103: ='Danh mục lỗi'!B9 -> XML3_OVERLAPPING_BED_USAGE | B103: ='Danh mục lỗi'!G9 -> 8117 | C103: ='Danh mục lỗi'!G9/$B$30 -> 0.33867401 | D103: ='Danh mục lỗi'!L9 -> Phòng BHYT | E103: ='Danh mục lỗi'!D9 -> Giường sử dụng trùng lặp
A104: ='Danh mục lỗi'!B12 -> XML8_TOMTAT_KQ_TOO_SHORT | B104: ='Danh mục lỗi'!G12 -> 7258 | C104: ='Danh mục lỗi'!G12/$B$30 -> 0.30283306 | D104: ='Danh mục lỗi'!L12 -> Khoa lâm sàng | E104: ='Danh mục lỗi'!D12 -> Tóm tắt kết quả quá ngắn
A105: ='Danh mục lỗi'!B13 -> XML2_INVALID_DANG_BAO_CHE | B105: ='Danh mục lỗi'!G13 -> 7033 | C105: ='Danh mục lỗi'!G13/$B$30 -> 0.29344515 | D105: ='Danh mục lỗi'!L13 -> Khoa Dược | E105: ='Danh mục lỗi'!D13 -> Dạng bào chế không khớp danh mục
A106: ='Danh mục lỗi'!B14 -> XML3_NGAY_TH_YL_EQUALS_NGAY_KQ | B106: ='Danh mục lỗi'!G14 -> 6758 | C106: ='Danh mục lỗi'!G14/$B$30 -> 0.28197104 | D106: ='Danh mục lỗi'!L14 -> CNTT | E106: ='Danh mục lỗi'!D14 -> Thời gian thực hiện y lệnh trùng thời gian kết quả
A107: ='Danh mục lỗi'!B15 -> XML3_EXECUTION_TIME_UNDER_3MIN | B107: ='Danh mục lỗi'!G15 -> 4865 | C107: ='Danh mục lỗi'!G15/$B$30 -> 0.20298744 | D107: ='Danh mục lỗi'!L15 -> CNTT | E107: ='Danh mục lỗi'!D15 -> Thời gian thực hiện nhỏ hơn quy định
A108: ='Danh mục lỗi'!B16 -> XML3_SAME_DOCTOR_ORDER_AND_EXECUTE | B108: ='Danh mục lỗi'!G16 -> 4779 | C108: ='Danh mục lỗi'!G16/$B$30 -> 0.19939917 | D108: ='Danh mục lỗi'!L16 -> Khoa lâm sàng | E108: ='Danh mục lỗi'!D16 -> Bác sĩ vừa ra y lệnh vừa thực hiện
A110: 10. Chuyển biến sau khi sửa và nạp lại (cùng 23.254 hồ sơ có trong cả hai lần kiểm)
...

Sheet Tổng hợp
A1: TỔNG HỢP LỖI TIỀN GIÁM ĐỊNH THEO ĐƠN VỊ VÀ NHÓM LỖI
A2: Tự tính từ sheet "Danh mục lỗi" (23.967 hồ sơ BHYT ra viện 01/10–15/10/2026 (nạp lại ngày 16/10/2026)). Chỉ đếm mã lỗi đã phát sinh (Số hồ sơ > 0). "Lượt hồ sơ-lỗi" = tổng số hồ sơ của các mã, một hồ sơ nhiều lỗi được đếm nhiều lần.
A4: 1. Theo đơn vị chủ trì
A5: Đơn vị chủ trì | B5: Số mã lỗi phát sinh | C5: Trong đó chặn gửi | D5: Lượt hồ sơ-lỗi | E5: Lượt hồ sơ-lỗi chặn gửi | F5: Mã lỗi lớn nhất
A6: Phòng BHYT | B6: =COUNTIFS('Danh mục lỗi'!$L$5:$L$222,$A6,'Danh mục lỗi'!$G$5:$G$222,">0") -> 32 | C6: =COUNTIFS('Danh mục lỗi'!$L$5:$L$222,$A6,'Danh mục lỗi'!$G$5:$G$222,">0",'Danh mục lỗi'!$E$5:$E$222,"Có") -> 21 | D6: =SUMIFS('Danh mục lỗi'!$G$5:$G$222,'Danh mục lỗi'!$L$5:$L$222,$A6) -> 12127 | E6: =SUMIFS('Danh mục lỗi'!$G$5:$G$222,'Danh mục lỗi'!$L$5:$L$222,$A6,'Danh mục lỗi'!$E$5:$E$222,"Có") -> 1177 | F6: XML3_OVERLAPPING_BED_USAGE (8.117 HS)
A7: CNTT | B7: =COUNTIFS('Danh mục lỗi'!$L$5:$L$222,$A7,'Danh mục lỗi'!$G$5:$G$222,">0") -> 23 | C7: =COUNTIFS('Danh mục lỗi'!$L$5:$L$222,$A7,'Danh mục lỗi'!$G$5:$G$222,">0",'Danh mục lỗi'!$E$5:$E$222,"Có") -> 9 | D7: =SUMIFS('Danh mục lỗi'!$G$5:$G$222,'Danh mục lỗi'!$L$5:$L$222,$A7) -> 62282 | E7: =SUMIFS('Danh mục lỗi'!$G$5:$G$222,'Danh mục lỗi'!$L$5:$L$222,$A7,'Danh mục lỗi'!$E$5:$E$222,"Có") -> 10107 | F7: XML4_CHI_SO_EMPTY (17.415 HS)
A8: Khoa Dược | B8: =COUNTIFS('Danh mục lỗi'!$L$5:$L$222,$A8,'Danh mục lỗi'!$G$5:$G$222,">0") -> 8 | C8: =COUNTIFS('Danh mục lỗi'!$L$5:$L$222,$A8,'Danh mục lỗi'!$G$5:$G$222,">0",'Danh mục lỗi'!$E$5:$E$222,"Có") -> 1 | D8: =SUMIFS('Danh mục lỗi'!$G$5:$G$222,'Danh mục lỗi'!$L$5:$L$222,$A8) -> 17221 | E8: =SUMIFS('Danh mục lỗi'!$G$5:$G$222,'Danh mục lỗi'!$L$5:$L$222,$A8,'Danh mục lỗi'!$E$5:$E$222,"Có") -> 396 | F8: XML2_INVALID_DANG_BAO_CHE (7.033 HS)
A9: Phòng VT-TBYT | B9: =COUNTIFS('Danh mục lỗi'!$L$5:$L$222,$A9,'Danh mục lỗi'!$G$5:$G$222,">0") -> 6 | C9: =COUNTIFS('Danh mục lỗi'!$L$5:$L$222,$A9,'Danh mục lỗi'!$G$5:$G$222,">0",'Danh mục lỗi'!$E$5:$E$222,"Có") -> 2 | D9: =SUMIFS('Danh mục lỗi'!$G$5:$G$222,'Danh mục lỗi'!$L$5:$L$222,$A9) -> 19568 | E9: =SUMIFS('Danh mục lỗi'!$G$5:$G$222,'Danh mục lỗi'!$L$5:$L$222,$A9,'Danh mục lỗi'!$E$5:$E$222,"Có") -> 32 | F9: XML3_INFO_ERROR_MA_MAY_NOT_FOUND (18.854 HS)
A10: Phòng KHTH | B10: =COUNTIFS('Danh mục lỗi'!$L$5:$L$222,$A10,'Danh mục lỗi'!$G$5:$G$222,">0") -> 4 | C10: =COUNTIFS('Danh mục lỗi'!$L$5:$L$222,$A10,'Danh mục lỗi'!$G$5:$G$222,">0",'Danh mục lỗi'!$E$5:$E$222,"Có") -> 4 | D10: =SUMIFS('Danh mục lỗi'!$G$5:$G$222,'Danh mục lỗi'!$L$5:$L$222,$A10) -> 15601 | E10: =SUMIFS('Danh mục lỗi'!$G$5:$G$222,'Danh mục lỗi'!$L$5:$L$222,$A10,'Danh mục lỗi'!$E$5:$E$222,"Có") -> 15601 | F10: XML3_INVALID_MA_DICH_VU (7.344 HS)
A11: Phòng TCKT | B11: =COUNTIFS('Danh mục lỗi'!$L$5:$L$222,$A11,'Danh mục lỗi'!$G$5:$G$222,">0") -> 1 | C11: =COUNTIFS('Danh mục lỗi'!$L$5:$L$222,$A11,'Danh mục lỗi'!$G$5:$G$222,">0",'Danh mục lỗi'!$E$5:$E$222,"Có") -> 0 | D11: =SUMIFS('Danh mục lỗi'!$G$5:$G$222,'Danh mục lỗi'!$L$5:$L$222,$A11) -> 232 | E11: =SUMIFS('Danh mục lỗi'!$G$5:$G$222,'Danh mục lỗi'!$L$5:$L$222,$A11,'Danh mục lỗi'!$E$5:$E$222,"Có") -> 0 | F11: XML3_INVALID_APPROVED_DON_GIA_BH (232 HS)
A12: Phòng TCCB | B12: =COUNTIFS('Danh mục lỗi'!$L$5:$L$222,$A12,'Danh mục lỗi'!$G$5:$G$222,">0") -> 1 | C12: =COUNTIFS('Danh mục lỗi'!$L$5:$L$222,$A12,'Danh mục lỗi'!$G$5:$G$222,">0",'Danh mục lỗi'!$E$5:$E$222,"Có") -> 0 | D12: =SUMIFS('Danh mục lỗi'!$G$5:$G$222,'Danh mục lỗi'!$L$5:$L$222,$A12) -> 10455 | E12: =SUMIFS('Danh mục lỗi'!$G$5:$G$222,'Danh mục lỗi'!$L$5:$L$222,$A12,'Danh mục lỗi'!$E$5:$E$222,"Có") -> 0 | F12: XMLComplete_NVYT_KHONG_CO_TRONG_DM (10.455 HS)
A13: Khoa lâm sàng | B13: =COUNTIFS('Danh mục lỗi'!$L$5:$L$222,$A13,'Danh mục lỗi'!$G$5:$G$222,">0") -> 33 | C13: =COUNTIFS('Danh mục lỗi'!$L$5:$L$222,$A13,'Danh mục lỗi'!$G$5:$G$222,">0",'Danh mục lỗi'!$E$5:$E$222,"Có") -> 25 | D13: =SUMIFS('Danh mục lỗi'!$G$5:$G$222,'Danh mục lỗi'!$L$5:$L$222,$A13) -> 19204 | E13: =SUMIFS('Danh mục lỗi'!$G$5:$G$222,'Danh mục lỗi'!$L$5:$L$222,$A13,'Danh mục lỗi'!$E$5:$E$222,"Có") -> 2232 | F13: XML8_TOMTAT_KQ_TOO_SHORT (7.258 HS)
A14: Tiếp đón | B14: =COUNTIFS('Danh mục lỗi'!$L$5:$L$222,$A14,'Danh mục lỗi'!$G$5:$G$222,">0") -> 8 | C14: =COUNTIFS('Danh mục lỗi'!$L$5:$L$222,$A14,'Danh mục lỗi'!$G$5:$G$222,">0",'Danh mục lỗi'!$E$5:$E$222,"Có") -> 4 | D14: =SUMIFS('Danh mục lỗi'!$G$5:$G$222,'Danh mục lỗi'!$L$5:$L$222,$A14) -> 451 | E14: =SUMIFS('Danh mục lỗi'!$G$5:$G$222,'Danh mục lỗi'!$L$5:$L$222,$A14,'Danh mục lỗi'!$E$5:$E$222,"Có") -> 19 | F14: XML1_ADMIN_INFO_ERROR_SO_CCCD (420 HS)
A15: Đơn vị PM Tiền giám định | B15: =COUNTIFS('Danh mục lỗi'!$L$5:$L$222,$A15,'Danh mục lỗi'!$G$5:$G$222,">0") -> 0 | C15: =COUNTIFS('Danh mục lỗi'!$L$5:$L$222,$A15,'Danh mục lỗi'!$G$5:$G$222,">0",'Danh mục lỗi'!$E$5:$E$222,"Có") -> 0 | D15: =SUMIFS('Danh mục lỗi'!$G$5:$G$222,'Danh mục lỗi'!$L$5:$L$222,$A15) -> 0 | E15: =SUMIFS('Danh mục lỗi'!$G$5:$G$222,'Danh mục lỗi'!$L$5:$L$222,$A15,'Danh mục lỗi'!$E$5:$E$222,"Có") -> 0 | F15: (không còn lỗi)
A16: Tổng | B16: =SUM(B6:B15) -> 116 | C16: =SUM(C6:C15) -> 66 | D16: =SUM(D6:D15) -> 157141 | E16: =SUM(E6:E15) -> 29564
A18: 2. Theo nhóm lỗi (nghiệp vụ / kỹ thuật)
A19: Phân nhóm | B19: Số mã lỗi phát sinh | C19: Trong đó chặn gửi | D19: Lượt hồ sơ-lỗi | E19: Lượt hồ sơ-lỗi chặn gửi | F19: Ý nghĩa
A20: Nghiệp vụ – Chuyên môn lâm sàng | B20: =COUNTIFS('Danh mục lỗi'!$K$5:$K$222,$A20,'Danh mục lỗi'!$G$5:$G$222,">0") -> 33 | C20: =COUNTIFS('Danh mục lỗi'!$K$5:$K$222,$A20,'Danh mục lỗi'!$G$5:$G$222,">0",'Danh mục lỗi'!$E$5:$E$222,"Có") -> 25 | D20: =SUMIFS('Danh mục lỗi'!$G$5:$G$222,'Danh mục lỗi'!$K$5:$K$222,$A20) -> 19204 | E20: =SUMIFS('Danh mục lỗi'!$G$5:$G$222,'Danh mục lỗi'!$K$5:$K$222,$A20,'Danh mục lỗi'!$E$5:$E$222,"Có") -> 2232 | F20: Bác sĩ/điều dưỡng nhập thiếu, sai nội dung chuyên môn
A21: Nghiệp vụ – Quy định BHYT | B21: =COUNTIFS('Danh mục lỗi'!$K$5:$K$222,$A21,'Danh mục lỗi'!$G$5:$G$222,">0") -> 32 | C21: =COUNTIFS('Danh mục lỗi'!$K$5:$K$222,$A21,'Danh mục lỗi'!$G$5:$G$222,">0",'Danh mục lỗi'!$E$5:$E$222,"Có") -> 21 | D21: =SUMIFS('Danh mục lỗi'!$G$5:$G$222,'Danh mục lỗi'!$K$5:$K$222,$A21) -> 12127 | E21: =SUMIFS('Danh mục lỗi'!$G$5:$G$222,'Danh mục lỗi'!$K$5:$K$222,$A21,'Danh mục lỗi'!$E$5:$E$222,"Có") -> 1177 | F21: Khai sai quy định thanh toán BHYT (đối tượng, mức hưởng, ngày giường, công khám)
A22: Nghiệp vụ – Hành chính, tiếp đón | B22: =COUNTIFS('Danh mục lỗi'!$K$5:$K$222,$A22,'Danh mục lỗi'!$G$5:$G$222,">0") -> 8 | C22: =COUNTIFS('Danh mục lỗi'!$K$5:$K$222,$A22,'Danh mục lỗi'!$G$5:$G$222,">0",'Danh mục lỗi'!$E$5:$E$222,"Có") -> 4 | D22: =SUMIFS('Danh mục lỗi'!$G$5:$G$222,'Danh mục lỗi'!$K$5:$K$222,$A22) -> 451 | E22: =SUMIFS('Danh mục lỗi'!$G$5:$G$222,'Danh mục lỗi'!$K$5:$K$222,$A22,'Danh mục lỗi'!$E$5:$E$222,"Có") -> 19 | F22: Tiếp đón nhập thiếu thông tin hành chính
A23: Nghiệp vụ – Danh mục | B23: =COUNTIFS('Danh mục lỗi'!$K$5:$K$222,$A23,'Danh mục lỗi'!$G$5:$G$222,">0") -> 20 | C23: =COUNTIFS('Danh mục lỗi'!$K$5:$K$222,$A23,'Danh mục lỗi'!$G$5:$G$222,">0",'Danh mục lỗi'!$E$5:$E$222,"Có") -> 7 | D23: =SUMIFS('Danh mục lỗi'!$G$5:$G$222,'Danh mục lỗi'!$K$5:$K$222,$A23) -> 63077 | E23: =SUMIFS('Danh mục lỗi'!$G$5:$G$222,'Danh mục lỗi'!$K$5:$K$222,$A23,'Danh mục lỗi'!$E$5:$E$222,"Có") -> 16029 | F23: Danh mục thuốc, VTYT, DVKT, NVYT, TTB, giá chưa khớp danh mục BHXH phê duyệt
A24: Kỹ thuật – HIS | B24: =COUNTIFS('Danh mục lỗi'!$K$5:$K$222,$A24,'Danh mục lỗi'!$G$5:$G$222,">0") -> 11 | C24: =COUNTIFS('Danh mục lỗi'!$K$5:$K$222,$A24,'Danh mục lỗi'!$G$5:$G$222,">0",'Danh mục lỗi'!$E$5:$E$222,"Có") -> 4 | D24: =SUMIFS('Danh mục lỗi'!$G$5:$G$222,'Danh mục lỗi'!$K$5:$K$222,$A24) -> 16230 | E24: =SUMIFS('Danh mục lỗi'!$G$5:$G$222,'Danh mục lỗi'!$K$5:$K$222,$A24,'Danh mục lỗi'!$E$5:$E$222,"Có") -> 27 | F24: HIS không bắt buộc nhập, tính sai, xuất sai định dạng
A25: Kỹ thuật – Tích hợp HIS–PACS | B25: =COUNTIFS('Danh mục lỗi'!$K$5:$K$222,$A25,'Danh mục lỗi'!$G$5:$G$222,">0") -> 2 | C25: =COUNTIFS('Danh mục lỗi'!$K$5:$K$222,$A25,'Danh mục lỗi'!$G$5:$G$222,">0",'Danh mục lỗi'!$E$5:$E$222,"Có") -> 1 | D25: =SUMIFS('Danh mục lỗi'!$G$5:$G$222,'Danh mục lỗi'!$K$5:$K$222,$A25) -> 2242 | E25: =SUMIFS('Danh mục lỗi'!$G$5:$G$222,'Danh mục lỗi'!$K$5:$K$222,$A25,'Danh mục lỗi'!$E$5:$E$222,"Có") -> 432 | F25: PACS/RIS trả kết quả thiếu thông tin về HIS
A26: Kỹ thuật – Tích hợp HIS–LIS | B26: =COUNTIFS('Danh mục lỗi'!$K$5:$K$222,$A26,'Danh mục lỗi'!$G$5:$G$222,">0") -> 3 | C26: =COUNTIFS('Danh mục lỗi'!$K$5:$K$222,$A26,'Danh mục lỗi'!$G$5:$G$222,">0",'Danh mục lỗi'!$E$5:$E$222,"Có") -> 2 | D26: =SUMIFS('Danh mục lỗi'!$G$5:$G$222,'Danh mục lỗi'!$K$5:$K$222,$A26) -> 22259 | E26: =SUMIFS('Danh mục lỗi'!$G$5:$G$222,'Danh mục lỗi'!$K$5:$K$222,$A26,'Danh mục lỗi'!$E$5:$E$222,"Có") -> 4844 | F26: LIS trả kết quả thiếu mã/tên chỉ số, giá trị
A27: Kỹ thuật – Tích hợp HIS–PACS/LIS | B27: =COUNTIFS('Danh mục lỗi'!$K$5:$K$222,$A27,'Danh mục lỗi'!$G$5:$G$222,">0") -> 7 | C27: =COUNTIFS('Danh mục lỗi'!$K$5:$K$222,$A27,'Danh mục lỗi'!$G$5:$G$222,">0",'Danh mục lỗi'!$E$5:$E$222,"Có") -> 2 | D27: =SUMIFS('Danh mục lỗi'!$G$5:$G$222,'Danh mục lỗi'!$K$5:$K$222,$A27) -> 21551 | E27: =SUMIFS('Danh mục lỗi'!$G$5:$G$222,'Danh mục lỗi'!$K$5:$K$222,$A27,'Danh mục lỗi'!$E$5:$E$222,"Có") -> 4804 | F27: PACS và LIS cùng mắc: tài khoản máy thay mã CCHN, thiếu người thực hiện, mã máy, thời gian KQ
A28: Kỹ thuật – Phần mềm Tiền giám định | B28: =COUNTIFS('Danh mục lỗi'!$K$5:$K$222,$A28,'Danh mục lỗi'!$G$5:$G$222,">0") -> 0 | C28: =COUNTIFS('Danh mục lỗi'!$K$5:$K$222,$A28,'Danh mục lỗi'!$G$5:$G$222,">0",'Danh mục lỗi'!$E$5:$E$222,"Có") -> 0 | D28: =SUMIFS('Danh mục lỗi'!$G$5:$G$222,'Danh mục lỗi'!$K$5:$K$222,$A28) -> 0 | E28: =SUMIFS('Danh mục lỗi'!$G$5:$G$222,'Danh mục lỗi'!$K$5:$K$222,$A28,'Danh mục lỗi'!$E$5:$E$222,"Có") -> 0 | F28: Thiếu sót của chính phần mềm kiểm (danh mục CSKCB, mã thừa)
A29: Cộng Nghiệp vụ | B29: =COUNTIFS('Danh mục lỗi'!$J$5:$J$222,"Nghiệp vụ",'Danh mục lỗi'!$G$5:$G$222,">0") -> 93 | C29: =COUNTIFS('Danh mục lỗi'!$J$5:$J$222,"Nghiệp vụ",'Danh mục lỗi'!$G$5:$G$222,">0",'Danh mục lỗi'!$E$5:$E$222,"Có") -> 57 | D29: =SUMIFS('Danh mục lỗi'!$G$5:$G$222,'Danh mục lỗi'!$J$5:$J$222,"Nghiệp vụ") -> 94859 | E29: =SUMIFS('Danh mục lỗi'!$G$5:$G$222,'Danh mục lỗi'!$J$5:$J$222,"Nghiệp vụ",'Danh mục lỗi'!$E$5:$E$222,"Có") -> 19457
A30: Cộng Kỹ thuật | B30: =COUNTIFS('Danh mục lỗi'!$J$5:$J$222,"Kỹ thuật",'Danh mục lỗi'!$G$5:$G$222,">0") -> 23 | C30: =COUNTIFS('Danh mục lỗi'!$J$5:$J$222,"Kỹ thuật",'Danh mục lỗi'!$G$5:$G$222,">0",'Danh mục lỗi'!$E$5:$E$222,"Có") -> 9 | D30: =SUMIFS('Danh mục lỗi'!$G$5:$G$222,'Danh mục lỗi'!$J$5:$J$222,"Kỹ thuật") -> 62282 | E30: =SUMIFS('Danh mục lỗi'!$G$5:$G$222,'Danh mục lỗi'!$J$5:$J$222,"Kỹ thuật",'Danh mục lỗi'!$E$5:$E$222,"Có") -> 10107

Sheet Trọng tâm theo đơn vị
A1: TRỌNG TÂM CẦN XỬ LÝ THEO TỪNG ĐƠN VỊ (để báo cáo)
A2: Số liệu là số hồ sơ có lỗi trong 23.967 hồ sơ BHYT ra viện 01/10–15/10/2026 (nạp lại ngày 16/10/2026) (bộ kiểm commit 63e21fa8). Chi tiết từng mã ở sheet "Danh mục lỗi".
A4: STT | B4: Đơn vị | C4: Nhóm | D4: Vấn đề | E4: Mã lỗi / số hồ sơ | F4: Việc cần làm
A5: 1 | B5: CNTT + hãng PACS/LIS | C5: Kỹ thuật – Tích hợp HIS–PACS/LIS | D5: PACS/LIS trả TÀI KHOẢN MÁY thay mã CCHN người đọc kết quả: vietrad 2.460 HS, mitalab 866, sys 66; thêm tên đăng nhập cá nhân (pqa1, LQH, ntdh3…). Tổng ~3.274 HS | E5: XMLComplete_NVYT_SAI_DINH_DANG (BS đọc KQ XML4): 3.274 HS | F5: Kết nối PACS/LIS ánh xạ tài khoản → mã CCHN; cấm ký kết quả bằng tài khoản dùng chung
A6: 2 | B6: CNTT + hãng LIS (Mitalab) | C6: Kỹ thuật – Tích hợp HIS–LIS | D6: LIS trả chỉ số thiếu mã và tên chỉ số, 91% ở Tổng phân tích tế bào máu 22.0121.1369 (còn lại: đường máu mao mạch 01.0281.1510, khí máu 23.0103.1531) | E6: XML4_CHI_SO_EMPTY: 17.415 HS | F6: Bổ sung ánh xạ chỉ số trên LIS cho các xét nghiệm bị lỗi
A7: 3 | B7: CNTT | C7: Kỹ thuật – HIS | D7: HIS gửi số CCCD/mã BHXH (12 số) vào NGUOI_THUC_HIEN thay vì mã CCHN: 54 người, ~1.367 HS (4 người có trong DM NVYT theo số định danh) | E7: XMLComplete_NVYT_SAI_DINH_DANG (phần số định danh) | F7: Xuất mã CCHN/GPHN, không xuất số định danh
A8: 4 | B8: CNTT | C8: Kỹ thuật – HIS / thiết bị | D8: Giờ thực hiện DVKT ghi theo lúc bấm: < 3 phút, giờ thực hiện = giờ kết quả (Điện tim, Đường máu mao mạch tại giường) | E8: UNDER_3MIN 4.865; NGAY_TH_YL = NGAY_KQ 6.758; dài bất thường (mới, cảnh báo) 438 HS | F8: Lấy giờ bắt đầu/kết thúc thật từ thiết bị/phiếu thực hiện
A9: 5 | B9: CNTT | C9: Kỹ thuật – HIS | D9: Thiếu người thực hiện, mã máy, thủ trưởng đơn vị khi xuất XML (HIS không bắt buộc / chưa cấu hình người ký). Từ 15/10 quy tắc thiếu mã máy căn cứ danh mục DVKT cần mã máy (thay lọc theo nhóm 1/2/3) nên số hồ sơ thiếu mã máy tăng | E9: Người TH trống 3.105; mã máy trống 9.985; thủ trưởng đơn vị 373 HS | F9: Bắt buộc nhập trên HIS; cấu hình người ký thủ trưởng cho từng loại giấy
A10: 6 | B10: Phòng KHTH | C10: Nghiệp vụ – Danh mục | D10: Danh mục DVKT cơ sở 01929 thiếu (8.595 dòng so với 15.723 của 37470), nhiều mã CĐHA (X-quang ngực 18.0119.0028); tên DVKT khác tên phê duyệt | E10: INVALID_MA_DICH_VU 7.344; XML4 mã DV 7.332; sai tên 858 HS | F10: Nhập đủ danh mục DVKT đã phê duyệt cho 01929
A11: 7 | B11: Phòng TCCB + Phòng BHYT | C11: Nghiệp vụ – Danh mục | D11: NVYT (CCHN) chưa có/chưa được duyệt trên cổng BHXH; trạng thái duyệt trên cổng đổi từ 08/10 | E11: XMLComplete_NVYT_KHONG_CO_TRONG_DM 10.455 HS: người TH XML3 9.714; BS đọc KQ XML4 9.292; BS chỉ định XML3 1.535; XML5 1.159; XML2 1.134; XML14 407 | F11: Rà soát, đăng ký bổ sung NVYT lên cổng; cập nhật DM NVYT vào phần mềm
A12: 8 | B12: Phòng TCKT | C12: Nghiệp vụ – Danh mục | D12: Giá DVKT trên HIS cao hơn giá phê duyệt (chưa chặn gửi nhưng BHXH sẽ xuất toán phần chênh) | E12: XML3_INVALID_APPROVED_DON_GIA_BH: 232 HS | F12: Đối chiếu bảng giá
A13: 9 | B13: Phòng VT-TBYT | C13: Nghiệp vụ – Danh mục | D13: Danh mục trang thiết bị (mã máy) chưa đủ; VTYT ngoài danh mục / sai tên / vượt giá | E13: Mã máy không có 18.854; VTYT ngoài DM 72; sai tên 475 HS | F13: Cập nhật danh mục TTB, VTYT theo thầu
A14: 10 | B14: Khoa Dược | C14: Nghiệp vụ – Danh mục | D14: Thuốc lệch danh mục được duyệt: dạng bào chế, ĐVT, đường dùng, tên, mã, thầu, SĐK, hàm lượng, giá | E14: Dạng bào chế 7.033; ĐVT: đã tắt kiểm 15/10; đường dùng 2.231; mã 396; tên 2.089 HS | F14: Đối chiếu, sửa danh mục thuốc HIS (luật hàm lượng/thầu đã sửa 12/10 – số liệu trước đó có báo nhầm)
A15: 11 | B15: Phòng BHYT | C15: Nghiệp vụ – Quy định BHYT | D15: Ngày giường (trùng giường, thiếu so với TT39, chưa khai ngày cộng thêm), thừa công khám nội trú, mức hưởng vượt quyền lợi thẻ, PT lần 2 thanh toán 100% | E15: Trùng giường 8.117; ngày cộng TT39 1.264; thừa công khám 480; mức hưởng 514 HS | F15: Rà quy tắc ngày giường/công khám/mức hưởng trên HIS cùng CNTT; giám sát tiếp đón
A16: 12 | B16: Khoa lâm sàng (qua Phòng KHTH) | C16: Nghiệp vụ – Chuyên môn lâm sàng | D16: Bác sĩ chỉ định = người thực hiện; tóm tắt kết quả ghi "xem hs BA"; diễn biến sao chép; liều dùng sai định dạng; thiếu PP điều trị | E16: Cùng BS 4.779; tóm tắt ngắn 7.258; diễn biến trùng 1.583 HS | F16: Phổ biến quy định, kiểm tra hồ sơ trước khi khoá bệnh án
... A18: 14 | B18: Đơn vị PM Tiền giám định | C18: Kỹ thuật – Phần mềm | D18: Cơ sở 37470 từng chưa có trong danh mục CSKCB của phần mềm kiểm → chặn oan. ĐÃ XỬ LÝ: kiểm lại 16/10/2026 không còn hồ sơ lỗi | E18: XML1_ADMIN_INFO_ERROR_MA_CSKCB_NOT_FOUND: 0 HS | F18: Đã bổ sung 37470 vào DM CSKCB — không cần xử lý thêm

Sheet Tài khoản thay CCHN
A1: MÃ NGƯỜI ĐỌC KẾT QUẢ / NGƯỜI THỰC HIỆN KHÔNG PHẢI MÃ CCHN
A2: Tách từ XMLComplete_NVYT_SAI_DINH_DANG (từ 15/10/2026 thay XML4_INFO_ERROR_MA_BS_DOC_KQ_NOT_FOUND và XML3_INFO_ERROR_NGUOI_THUC_HIEN_NOT_FOUND), 23.967 hồ sơ BHYT ra viện 01/10–15/10/2026 (nạp lại ngày 16/10/2026).
A4: Giá trị gửi lên | B4: Trường | C4: Số hồ sơ | D4: Loại | E4: Nguồn | F4: Dịch vụ điển hình | G4: Xử lý
A5: vietrad | B5: MA_BS_DOC_KQ (XML4) | C5: 2460 | D5: Tài khoản hệ thống PACS | E5: Tích hợp HIS–PACS | F5: Siêu âm ổ bụng 18.0015.0001; X-quang ngực thẳng 18.0119.0028 | G5: PACS trả mã CCHN của bác sĩ ký kết quả
A6: mitalab | B6: MA_BS_DOC_KQ (XML4) | C6: 866 | D6: Tài khoản hệ thống LIS | E6: Tích hợp HIS–LIS | F6: Tổng phân tích tế bào máu 22.0121.1369; Khí máu 23.0103.1531; Tủy đồ 22.0129.1415 | G6: LIS trả mã CCHN của người duyệt kết quả
A7: sys | B7: MA_BS_DOC_KQ (XML4) | C7: 66 | D7: Tài khoản quản trị | E7: Tích hợp HIS–PACS | F7: Siêu âm ổ bụng, Siêu âm tuyến giáp | G7: Không cho ký kết quả bằng tài khoản quản trị
A8: pqa1, LQH, ntdh3, phn3, dtt15, vttq2, TTH39, dsl, vannh, hvh3, bvt, pat, pthai, dht1, ptc4, ndb11, ntt73, nxg… | B8: MA_BS_DOC_KQ (XML4) | C8: 208 | D8: Tên đăng nhập cá nhân | E8: Tích hợp HIS–PACS/LIS | F8: X-quang (PACS) … | G8: Ánh xạ tên đăng nhập → mã CCHN
A9: 028322, 32161, 25092, 028605… | B9: MA_BS_DOC_KQ (XML4) | C9: 21 | D9: Số thiếu phần /BYT-CCHN | E9: Tích hợp HIS–PACS/LIS | G9: Trả đủ mã CCHN
A10: Số CCCD/mã BHXH 12 chữ số (54 người) | B10: NGUOI_THUC_HIEN (XML3) | C10: 1367 | D10: Số định danh thay mã CCHN | E10: HIS | G10: HIS xuất mã CCHN/GPHN; 4 người khớp DM NVYT theo số định danh
A11: CNTT | B11: NGUOI_THUC_HIEN (XML3) | C11: 1 | D11: Tài khoản dùng chung | E11: HIS | G11: Không cho tài khoản CNTT thực hiện DVKT
A13: Ghi chú: mã CCHN đúng định dạng nhưng chưa có/chưa được duyệt trong danh mục NVYT (XMLComplete_NVYT_KHONG_CO_TRONG_DM) – BS đọc KQ XML4: 43 mã, 9.292 HS; người thực hiện XML3: 65 mã, 9.714 HS → thuộc Phòng TCCB/Phòng BHYT.

Sheet Danh mục lỗi
A1: PHÂN LOẠI DANH MỤC LỖI XML3176 THEO NGUỒN PHÁT SINH VÀ ĐƠN VỊ XỬ LÝ
A2: Số hồ sơ: 23.967 hồ sơ BHYT ra viện 01/10–15/10/2026 (nạp lại ngày 16/10/2026), kiểm lại bằng bộ kiểm hiện tại (commit 63e21fa8, chế độ chỉ đọc) ngày 16/10/2026, không lỗi chạy. Cột P = số hồ sơ của CÙNG nhóm hồ sơ khi kiểm sáng 16/10, trước khi nạp lại (23.254 hồ sơ có trong lần kiểm đó) – để thấy lỗi nào đã giảm sau khi sửa. Đã bỏ 37 mã cũ không còn dùng (đã gộp vào mã mới hoặc đang tắt kiểm). Một hồ sơ có thể mang nhiều mã lỗi nên không cộng dồn số hồ sơ giữa các dòng.
A4: STT | B4: Mã lỗi | C4: XML | D4: Tên lỗi | E4: Chặn gửi | F4: Đang kiểm | G4: Số hồ sơ | H4: % hồ sơ | I4: Ví dụ thực tế | J4: Nhóm lớn | K4: Phân nhóm | L4: Đơn vị chủ trì | M4: Đơn vị phối hợp | N4: Hướng xử lý | O4: FIXERROR hệ thống khác tự sửa (quy tắc số) | P4: Số HS trước khi nạp lại (kiểm sáng 16/10)
A5: 1 | B5: XML3_INFO_ERROR_MA_MAY_NOT_FOUND | C5: XML3 | D5: Mã máy không tồn tại trong danh mục trang thiết bị | E5: Không | F5: Có | G5: 18854 | H5: =G5/23967 -> 0.786665 | I5: Mã máy không tồn tại: ĐX.2.000895 | J5: Nghiệp vụ | K5: Nghiệp vụ – Danh mục | L5: Phòng VT-TBYT | M5: Phòng BHYT; CNTT | N5: Cập nhật danh mục trang thiết bị (mã máy) lên cổng và vào phần mềm | P5: 18264
A6: 2 | B6: XML4_CHI_SO_EMPTY | C6: XML4 | D6: Mã/tên chỉ số để trống | E6: Không | F6: Có | G6: 17415 | H6: =G6/23967 -> 0.72662411 | I6: Dòng có giá trị/đơn vị đo nhưng thiếu mã chỉ số và tên chỉ số. Dịch vụ: 22.0121.1369 | J6: Kỹ thuật | K6: Kỹ thuật – Tích hợp HIS–LIS | L6: CNTT | M6: Hãng LIS (Mitalab); Khoa Xét nghiệm | N6: Bổ sung ánh xạ mã/tên chỉ số trên kết nối LIS → HIS (gộp hai mã cũ mã chỉ số trống + tên chỉ số trống từ 15/10) | P6: 16844
A7: 3 | B7: XMLComplete_NVYT_KHONG_CO_TRONG_DM | C7: XMLComplete | D7: Mã nhân viên y tế không có trong danh mục NVYT | E7: Không | F7: Có | G7: 10455 | H7: =G7/23967 -> 0.43622481 | I7: 032154/BYT-CCHN không có trong danh mục NVYT — người thực hiện XML3 (1 dòng: Siêu âm doppler tim, van tim), BS đọc KQ XML4 (1 dòng: 18.0052.0004) | J7: Nghiệp vụ | K7: Nghiệp vụ – Danh mục | L7: Phòng TCCB | M7: Phòng BHYT; CNTT | N7: Rà soát, đăng ký bổ sung NVYT lên cổng; cập nhật DM NVYT vào phần mềm (gộp các mã NVYT "không tồn tại" cũ từ 15/10) | O7: #35 | P7: 10181
A8: 4 | B8: XML3_INFO_ERROR_GROUP_CODE_MA_MAY | C8: XML3 | D8: Thiếu mã máy | E8: Không | F8: Có | G8: 9985 | H8: =G8/23967 -> 0.41661451 | I8: Mã máy không được để trống đối với DVKT: Đốt sóng cao tần điều trị ung thư gan (RFA) dưới hướng dẫn siêu âm (mã 18.0614.0063) | J8: Kỹ thuật | K8: Kỹ thuật – Tích hợp HIS–PACS/LIS | L8: CNTT | M8: Phòng VT-TBYT; Hãng PACS; Hãng LIS | N8: Kết nối thiết bị/PACS/LIS trả mã máy thực hiện; HIS bắt buộc mã máy với DVKT yêu cầu | P8: 9717
A9: 5 | B9: XML3_OVERLAPPING_BED_USAGE | C9: XML3 | D9: Giường sử dụng trùng lặp | E9: Không | F9: Có | G9: 8117 | H9: =G9/23967 -> 0.33867401 | I9: Giường T008 tại khoa K14 sử dụng trùng lặp trong khoảng thời gian từ 09/10/2026 20:49 đến 10/10/2026 20:49. Trùng lặp với hồ sơ có mã: 000007379048 (NGAY_TH_YL: 10/10/2026 11:00, NGAY_KQ: 10/10/2026 1 | J9: Nghiệp vụ | K9: Nghiệp vụ – Quy định BHYT | L9: Phòng BHYT | M9: Khoa lâm sàng; CNTT | N9: Rà soát chỉ định ngày giường, công khám, khoa chỉ định đúng quy định BHYT | P9: 7727
A10: 6 | B10: XML3_INVALID_MA_DICH_VU | C10: XML3 | D10: Mã dịch vụ không tồn tại | E10: Có | F10: Có | G10: 7344 | H10: =G10/23967 -> 0.30642133 | I10: Dịch vụ không tồn tại trong DM DVKT: _TB | J10: Nghiệp vụ | K10: Nghiệp vụ – Danh mục | L10: Phòng KHTH | M10: Phòng BHYT; CNTT | N10: Nhập đủ danh mục DVKT đã được BHXH phê duyệt (cơ sở 01929 chỉ có 8.123 dòng so với 15.660 của 37470); tên DVKT trên HIS theo đúng tên phê duyệt | P10: 7177
A11: 7 | B11: XML4_INFO_ERROR_MA_DICH_VU_NOT_FOUND | C11: XML4 | D11: Mã dịch vụ không tồn tại | E11: Có | F11: Có | G11: 7332 | H11: =G11/23967 -> 0.30592064 | I11: Mã dịch vụ không tồn tại trong danh mục DVKT: 24.0108.1720.SC2 | J11: Nghiệp vụ | K11: Nghiệp vụ – Danh mục | L11: Phòng KHTH | M11: Phòng BHYT; CNTT | N11: Nhập đủ danh mục DVKT đã được BHXH phê duyệt (cơ sở 01929 chỉ có 8.123 dòng so với 15.660 của 37470); tên DVKT trên HIS theo đúng tên phê duyệt | P11: 7167
A12: 8 | B12: XML8_TOMTAT_KQ_TOO_SHORT | C12: XML8 | D12: Tóm tắt kết quả quá ngắn | E12: Không | F12: Có | G12: 7258 | H12: =G12/23967 -> 0.30283306 | I12: Tóm tắt kết quả chỉ 9 ký tự (< 20): "xem hs BA" | J12: Nghiệp vụ | K12: Nghiệp vụ – Chuyên môn lâm sàng | L12: Khoa lâm sàng | M12: Phòng KHTH | N12: Bác sĩ nhập đủ, đúng nội dung chuyên môn trên HIS; Phòng KHTH kiểm tra | O12: #47 | P12: 6815
A13: 9 | B13: XML2_INVALID_DANG_BAO_CHE | C13: XML2 | D13: Dạng bào chế không khớp danh mục | E13: Không | F13: Có | G13: 7033 | H13: =G13/23967 -> 0.29344515 | I13: Mã thuốc: 40.980; Dạng bào chế không khớp danh mục: "Hỗn dịch xịt qua bình định kiều điều áp" # danh mục: "Hỗn dịch xịt qua bình định liều điều áp" | J13: Nghiệp vụ | K13: Nghiệp vụ – Danh mục | L13: Khoa Dược | M13: Phòng BHYT; CNTT | N13: Khoa Dược đối chiếu danh mục thuốc trên HIS với danh mục được duyệt (mã, tên, hàm lượng, SĐK, thầu, đường dùng, dạng bào chế, ĐVT, giá) | P13: 6778
A14: 10 | B14: XML3_NGAY_TH_YL_EQUALS_NGAY_KQ | C14: XML3 | D14: Thời gian thực hiện y lệnh trùng thời gian kết quả | E14: Không | F14: Có | G14: 6758 | H14: =G14/23967 -> 0.28197104 | I14: NGAY_TH_YL = NGAY_KQ = 31/08/2026 23:11. Dịch vụ: Xét nghiệm đường máu mao mạch tại giường (một lần) | J14: Kỹ thuật | K14: Kỹ thuật – HIS | L14: CNTT | M14: Khoa lâm sàng; Khoa thăm dò chức năng | N14: Giờ bắt đầu/kết thúc phải là giờ thực hiện thật, không lấy giờ bấm trả kết quả (Điện tim, Đường máu mao mạch tại giường…) | O14: #33 | P14: 6475
A15: 11 | B15: XML3_EXECUTION_TIME_UNDER_3MIN | C15: XML3 | D15: Thời gian thực hiện nhỏ hơn quy định | E15: Không | F15: Có | G15: 4865 | H15: =G15/23967 -> 0.20298744 | I15: Nhóm 3: thực hiện 2 phút (< 3). Dịch vụ: Đo đa ký hô hấp | J15: Kỹ thuật | K15: Kỹ thuật – HIS | L15: CNTT | M15: Khoa lâm sàng; Khoa thăm dò chức năng | N15: Giờ bắt đầu/kết thúc phải là giờ thực hiện thật, không lấy giờ bấm trả kết quả (Điện tim, Đường máu mao mạch tại giường…) | O15: #33 | P15: 4685
A16: 12 | B16: XML3_SAME_DOCTOR_ORDER_AND_EXECUTE | C16: XML3 | D16: Bác sĩ vừa ra y lệnh vừa thực hiện | E16: Không | F16: Có | G16: 4779 | H16: =G16/23967 -> 0.19939917 | I16: Mã bác sĩ = người thực hiện = 5301/BP-CCHN. Dịch vụ: Định nhóm máu tại giường bệnh trước truyền máu [khối hồng cầu, khối bạch cầu] | J16: Nghiệp vụ | K16: Nghiệp vụ – Chuyên môn lâm sàng | L16: Khoa lâm sàng | M16: Phòng KHTH; CNTT | N16: Rà soát quy trình chỉ định – thực hiện; không gán giờ/người đồng loạt | O16: #35 | P16: 4694
A17: 13 | B17: XMLComplete_NVYT_SAI_DINH_DANG | C17: XMLComplete | D17: Mã nhân viên y tế sai định danh | E17: Không | F17: Có | G17: 4141 | H17: =G17/23967 -> 0.17277924 | I17: vietrad là tài khoản/tên đăng nhập, không phải mã CCHN — BS đọc KQ XML4 (1 dòng: 18.0015.0001) | J17: Kỹ thuật | K17: Kỹ thuật – Tích hợp HIS–PACS/LIS | L17: CNTT | M17: Hãng PACS (Vietrad); Hãng LIS (Mitalab); Phòng TCCB | N17: PACS/LIS/HIS trả mã CCHN thay cho tài khoản/số định danh – xem sheet "Tài khoản thay CCHN" | O17: #39 | P17: 4401
A18: 14 | B18: XML2_LIEU_DUNG_UNIT_INVALID | C18: XML2 | D18: Đơn vị trong liều dùng khác đơn vị tính của thuốc | E18: Không | F18: Có | G18: 4025 | H18: =G18/23967 -> 0.16793925 | I18: Đơn vị trong liều dùng (Ống) khác đơn vị tính của thuốc (Đơn vị) | J18: Kỹ thuật | K18: Kỹ thuật – HIS | L18: CNTT | M18: Phòng KHTH; Khoa Dược | N18: Sửa ánh xạ/định dạng dữ liệu khi HIS xuất XML; bắt buộc nhập trường còn thiếu | P18: 3847
A19: 15 | B19: XML4_XN_MISSING_VALUE_RESULT | C19: XML4 | D19: Xét nghiệm không nhập giá trị và kết quả | E19: Có | F19: Có | G19: 3753 | H19: =G19/23967 -> 0.15659031 | I19: Chỉ số Đo độ ngưng tập tiểu cầu với Ristocetin trong huyết tương giàu tiểu cầu không có giá trị/mô tả/kết luận. Dịch vụ: 22.0042.1288 | J19: Kỹ thuật | K19: Kỹ thuật – Tích hợp HIS–LIS | L19: CNTT | M19: Hãng LIS (Mitalab); Khoa Xét nghiệm | N19: LIS trả đủ giá trị/kết luận theo chỉ số; kết quả dạng chữ (vi sinh) đưa vào KET_LUAN/MO_TA | P19: 3845
A20: 16 | B20: XMLComplete_NVYT_THIEU | C20: XMLComplete | D20: Thiếu mã nhân viên y tế | E20: Có | F20: Có | G20: 3533 | H20: =G20/23967 -> 0.14741102 | I20: Thiếu mã người thực hiện ở 1 dòng: XML3 (1 dòng: Siêu âm ổ bụng (gan mật, tụy, lách, thận, bàng quang)). | J20: Kỹ thuật | K20: Kỹ thuật – Tích hợp HIS–PACS/LIS | L20: CNTT | M20: Khoa Xét nghiệm; Khoa CĐHA; Khoa lâm sàng | N20: Bắt buộc nhập người thực hiện/BS đọc KQ trên HIS; cấu hình người ký thủ trưởng (gộp các mã NVYT "để trống" cũ từ 15/10) | O20: #35 | P20: 4050
A21: 17 | B21: XML2_INVALID_DRUG_CONCENTRATION | C21: XML2 | D21: Mã thuốc sai hàm lượng trong danh mục BHYT | E21: Không | F21: Có | G21: 2810 | H21: =G21/23967 -> 0.11724454 | I21: Mã thuốc: 40.980; Sai hàm lượng: 5mg/2,5ml | J21: Nghiệp vụ | K21: Nghiệp vụ – Danh mục | L21: Khoa Dược | M21: Phòng BHYT; CNTT | N21: Khoa Dược đối chiếu danh mục thuốc trên HIS với danh mục được duyệt (mã, tên, hàm lượng, SĐK, thầu, đường dùng, dạng bào chế, ĐVT, giá) | P21: 2718
A22: 18 | B22: XML2_INVALID_DUONG_DUNG | C22: XML2 | D22: Đường dùng không khớp danh mục | E22: Không | F22: Có | G22: 2231 | H22: =G22/23967 -> 0.093086327 | I22: Mã thuốc: 40.883; Đường dùng không khớp danh mục: "6.01" # danh mục: "Dùng ngoài / 3.05" | J22: Nghiệp vụ | K22: Nghiệp vụ – Danh mục | L22: Khoa Dược | M22: Phòng BHYT; CNTT | N22: Khoa Dược đối chiếu danh mục thuốc trên HIS với danh mục được duyệt (mã, tên, hàm lượng, SĐK, thầu, đường dùng, dạng bào chế, ĐVT, giá) | P22: 2154
A23: 19 | B23: XML2_INVALID_DRUG_NAME | C23: XML2 | D23: Mã thuốc sai tên trong danh mục BHYT | E23: Không | F23: Có | G23: 2089 | H23: =G23/23967 -> 0.087161514 | I23: Mã thuốc: 40.974; Thuốc sai tên so với danh mục được duyệt: Symbicort Turbuhaler # Symbicort Turbuhaler 60 Dose 160/4.5 | J23: Nghiệp vụ | K23: Nghiệp vụ – Danh mục | L23: Khoa Dược | M23: Phòng BHYT; CNTT | N23: Khoa Dược đối chiếu danh mục thuốc trên HIS với danh mục được duyệt (mã, tên, hàm lượng, SĐK, thầu, đường dùng, dạng bào chế, ĐVT, giá) | P23: 2043
A24: 20 | B24: XML3_INVALID_NGAY_KQ | C24: XML3 | D24: Ngày trả kết quả không hợp lệ | E24: Không | F24: Có | G24: 2031 | H24: =G24/23967 -> 0.08474152 | I24: Ngày trả kết quả (NGAY_KQ) không nằm trong khoảng thời gian vào (31/08/2026 08:54) và ra (08/09/2026 15:50) | J24: Kỹ thuật | K24: Kỹ thuật – Tích hợp HIS–PACS/LIS | L24: CNTT | M24: Khoa CĐHA; Khoa Xét nghiệm | N24: Thống nhất một nguồn thời gian trả kết quả giữa PACS/LIS và HIS; rà ca trả kết quả sau ra viện | O24: #32 | P24: 1110
A25: 21 | B25: XML4_INFO_ERROR_MO_TA_EMPTY | C25: XML4 | D25: Mô tả không được để trống | E25: Không | F25: Có | G25: 1810 | H25: =G25/23967 -> 0.075520507 | I25: Mô tả không được để trống đối với DVKT: 19.0222.0050.K.01916 | J25: Kỹ thuật | K25: Kỹ thuật – Tích hợp HIS–PACS | L25: CNTT | M25: Hãng PACS; Khoa CĐHA; Khoa Y học hạt nhân | N25: PACS/RIS trả đủ mô tả và kết luận; khoa CĐHA không duyệt kết quả trống | P25: 1691
A26: 22 | B26: XML5_DIEN_BIEN_DUPLICATE | C26: XML5 | D26: Diễn biến điều trị trùng nhau | E26: Không | F26: Có | G26: 1583 | H26: =G26/23967 -> 0.066049151 | I26: Diễn biến lâm sàng trùng với dòng STT 9: "Diễn biến: Y lệnh thuốc; Theo dõi - chăm sóc: Chăm sóc cấp 2 Chế độ ăn BT05 Theo dõi toàn trạng, mạ" | J26: Nghiệp vụ | K26: Nghiệp vụ – Chuyên môn lâm sàng | L26: Khoa lâm sàng | M26: Phòng KHTH | N26: Bác sĩ nhập đủ, đúng nội dung chuyên môn trên HIS; Phòng KHTH kiểm tra | P26: 1522
A27: 23 | B27: XML2_PRICE_EXCEEDS_APPROVED | C27: XML2 | D27: Giá thuốc cao hơn giá được duyệt | E27: Không | F27: Có | G27: 1578 | H27: =G27/23967 -> 0.065840531 | I27: Mã thuốc: 40.974; Giá cao hơn giá được duyệt: 434000 > 219000.00 | J27: Nghiệp vụ | K27: Nghiệp vụ – Danh mục | L27: Khoa Dược | M27: Phòng BHYT; CNTT | N27: Khoa Dược đối chiếu danh mục thuốc trên HIS với danh mục được duyệt (mã, tên, hàm lượng, SĐK, thầu, đường dùng, dạng bào chế, ĐVT, giá) | P27: 1524
A28: 24 | B28: XML3_SERVICE_GROUP_PTTT_DUPLICATE | C28: XML3 | D28: PTTT trùng y lệnh | E28: Không | F28: Có | G28: 1432 | H28: =G28/23967 -> 0.059748821 | I28: - Mã điều trị=000007450973; stt=9; Bác sĩ=047397/BYT-CCHN; Ngày yl=13/10/2026 16:56; Ngày th=13/10/2026 16:56; Ngày kq=13/10/2026 17:00 | J28: Nghiệp vụ | K28: Nghiệp vụ – Chuyên môn lâm sàng | L28: Khoa lâm sàng | M28: Phòng KHTH; CNTT | N28: Rà soát quy trình chỉ định – thực hiện; không gán giờ/người đồng loạt | P28: 1372
A29: 25 | B29: XML3_OVERLAPPING_SERVICE_EXECUTION | C29: XML3 | D29: Thời gian thực hiện trùng với dịch vụ khác | E29: Không | F29: Có | G29: 1296 | H29: =G29/23967 -> 0.054074352 | I29: Dịch vụ 28.0110.0584 (20/09/2026 00:11 - 20/09/2026 00:31) chồng thời gian thực hiện với dịch vụ 15.0301.0218 (20/09/2026 00:11 - 20/09/2026 00:31) trong cùng hồ sơ. | J29: Nghiệp vụ | K29: Nghiệp vụ – Chuyên môn lâm sàng | L29: Khoa lâm sàng | M29: Phòng KHTH; CNTT | N29: Rà soát quy trình chỉ định – thực hiện; không gán giờ/người đồng loạt | P29: 1260
A30: 26 | B30: XML4_INFO_ERROR_NGAY_KQ | C30: XML4 | D30: Thiếu ngày trả kết quả | E30: Có | F30: Có | G30: 1271 | H30: =G30/23967 -> 0.053031251 | I30: Ngày trả kết quả không được để trống | J30: Kỹ thuật | K30: Kỹ thuật – Tích hợp HIS–PACS/LIS | L30: CNTT | M30: Hãng PACS; Hãng LIS; Khoa CĐHA; Khoa Xét nghiệm | N30: Bắt buộc ký số/duyệt kết quả trên PACS/LIS trước khi đẩy về HIS | O30: #38 | P30: 1912
A31: 27 | B31: XMLComplete_BED_DAYS_SPECIAL_NOT_CLAIMED | C31: XMLComplete | D31: Trường hợp đặc biệt được cộng 1 ngày giường nhưng chưa khai | E31: Không | F31: Có | G31: 1264 | H31: =G31/23967 -> 0.052739183 | I31: Được cộng 1 ngày giường theo TT39 (loại ra viện 4 - Xin ra viện): được 9, đã khai 8 — chưa khai ngày được cộng thêm. | J31: Nghiệp vụ | K31: Nghiệp vụ – Quy định BHYT | L31: Phòng BHYT | M31: CNTT; Phòng TCKT | N31: Sửa cách HIS tính ngày giường theo TT39 / thanh toán PT lần 2 trong ngày | P31: 1214
A32: 28 | B32: XML4_INFO_ERROR_GIA_TRI_LENGTH | C32: XML4 | D32: Giá trị quá dài | E32: Có | F32: Có | G32: 1091 | H32: =G32/23967 -> 0.045520925 | I32: Giá trị không được lớn hơn 50 kí tự: Vi khuẩn:Cầu trực khuẩn Gram (-) 1(+) Bạch cầu đa nhân: ( ++) | J32: Kỹ thuật | K32: Kỹ thuật – Tích hợp HIS–LIS | L32: CNTT | M32: Hãng LIS (Mitalab); Khoa Xét nghiệm | N32: LIS trả đủ giá trị/kết luận theo chỉ số; kết quả dạng chữ (vi sinh) đưa vào KET_LUAN/MO_TA | O32: #37 | P32: 1007
A33: 29 | B33: XML2_INVALID_REGISTRATION_NUMBER | C33: XML2 | D33: Mã thuốc sai số đăng ký trong danh mục BHYT | E33: Không | F33: Có | G33: 997 | H33: =G33/23967 -> 0.041598865 | I33: Mã thuốc: 40.692; Số ĐK: 300110997524 | J33: Nghiệp vụ | K33: Nghiệp vụ – Danh mục | L33: Khoa Dược | M33: Phòng BHYT; CNTT | N33: Khoa Dược đối chiếu danh mục thuốc trên HIS với danh mục được duyệt (mã, tên, hàm lượng, SĐK, thầu, đường dùng, dạng bào chế, ĐVT, giá) | P33: 988
A34: 30 | B34: XML3_INVALID_TEN_DICH_VU | C34: XML3 | D34: Tên dịch vụ kỹ thuật khác tên được phê duyệt | E34: Có | F34: Có | G34: 858 | H34: =G34/23967 -> 0.035799224 | I34: Mã DVKT: 22.0307.1306 có tên: Nghiệm pháp Coombs gián tiếp (Kỹ thuật Scangel/Gelcard trên máy tự động); Tên phê duyệt: Nghiệm pháp Coombs gián tiếp (kỹ thuật Scangel/Gelcard trên máy tự động) | J34: Nghiệp vụ | K34: Nghiệp vụ – Danh mục | L34: Phòng KHTH | M34: Phòng BHYT; CNTT | N34: Nhập đủ danh mục DVKT đã được BHXH phê duyệt (cơ sở 01929 chỉ có 8.123 dòng so với 15.660 của 37470); tên DVKT trên HIS theo đúng tên phê duyệt | P34: 828
A35: 31 | B35: XML3_BED_DAY_QUANTITY_ERROR | C35: XML3 | D35: Chỉ định ngày giường > 1 | E35: Không | F35: Có | G35: 857 | H35: =G35/23967 -> 0.0357575 | I35: Số lượng ngày giường > 1. Ngày y lệnh: 31/08/2026 07:58 | J35: Nghiệp vụ | K35: Nghiệp vụ – Quy định BHYT | L35: Phòng BHYT | M35: Khoa lâm sàng; CNTT | N35: Rà soát chỉ định ngày giường, công khám, khoa chỉ định đúng quy định BHYT | P35: 837
A36: 32 | B36: XML7_INFO_ERROR_PP_DIEUTRI | C36: XML7 | D36: Thiếu phương pháp điều trị | E36: Có | F36: Có | G36: 642 | H36: =G36/23967 -> 0.026786832 | I36: Phương pháp điều trị không được để trống | J36: Nghiệp vụ | K36: Nghiệp vụ – Chuyên môn lâm sàng | L36: Khoa lâm sàng | M36: Phòng KHTH | N36: Bác sĩ nhập đủ, đúng nội dung chuyên môn trên HIS; Phòng KHTH kiểm tra | O36: #44 | P36: 548
A37: 33 | B37: XML8_INFO_ERROR_PP_DIEUTRI | C37: XML8 | D37: Thiếu phương pháp điều trị | E37: Có | F37: Có | G37: 636 | H37: =G37/23967 -> 0.026536488 | I37: Phương pháp điều trị không được để trống | J37: Nghiệp vụ | K37: Nghiệp vụ – Chuyên môn lâm sàng | L37: Khoa lâm sàng | M37: Phòng KHTH | N37: Bác sĩ nhập đủ, đúng nội dung chuyên môn trên HIS; Phòng KHTH kiểm tra | O37: #47 | P37: 542
A38: 34 | B38: XMLComplete_XML4_NGAY_KQ_MISMATCH_XML3 | C38: XMLComplete | D38: Ngày KQ XML4 khác ngày KQ XML3 | E38: Không | F38: Có | G38: 582 | H38: =G38/23967 -> 0.02428339 | I38: Dịch vụ 19.0174.1866: ngày KQ XML4 (30/09/2026 15:06) khác ngày KQ XML3 | J38: Kỹ thuật | K38: Kỹ thuật – Tích hợp HIS–PACS/LIS | L38: CNTT | M38: Khoa CĐHA; Khoa Xét nghiệm | N38: Thống nhất một nguồn thời gian trả kết quả giữa PACS/LIS và HIS; rà ca trả kết quả sau ra viện | O38: #38 | P38: 491
A39: 35 | B39: XMLComplete_MUC_HUONG_EXCEEDS_ENTITLEMENT | C39: XMLComplete | D39: Mức hưởng khai vượt trần cho phép | E39: Có | F39: Có | G39: 514 | H39: =G39/23967 -> 0.021446155 | I39: Hồ sơ đúng tuyến: mức hưởng khai tối đa 100%, trần cho phép 95% (quyền lợi thẻ 95%). | J39: Nghiệp vụ | K39: Nghiệp vụ – Quy định BHYT | L39: Phòng BHYT | M39: Tiếp đón; CNTT | N39: Tiếp đón khai đúng mã đối tượng, giấy chuyển tuyến/hẹn, mức hưởng theo thẻ; HIS chặn khi thiếu | P39: 486
A40: 36 | B40: XMLComplete_ERROR_MULTIPLE_EXAMINATION_FEES_INPATIENT | C40: XMLComplete | D40: Thừa công khám cho Điều trị nội trú | E40: Có | F40: Có | G40: 480 | H40: =G40/23967 -> 0.020027538 | I40: Chỉ cho phép có một lần công khám, số lượng hiện tại: 5 | J40: Nghiệp vụ | K40: Nghiệp vụ – Quy định BHYT | L40: Phòng BHYT | M40: Khoa lâm sàng; CNTT | N40: Rà soát chỉ định ngày giường, công khám, khoa chỉ định đúng quy định BHYT | P40: 464
A41: 37 | B41: XML3_INVALID_MATERIAL_NAME | C41: XML3 | D41: Tên vật tư không khớp với danh mục phê duyệt | E41: Không | F41: Có | G41: 475 | H41: =G41/23967 -> 0.019818918 | I41: Mã VTYT: N08.00.310.3272.279.0002 có tên: Mặt nạ Oxy không túi các loại, các cỡ; Tên phê duyệt: Mask thở Oxy | J41: Nghiệp vụ | K41: Nghiệp vụ – Danh mục | L41: Phòng VT-TBYT | M41: Phòng BHYT; CNTT | N41: Đối chiếu danh mục VTYT trên HIS với danh mục được duyệt theo thầu | P41: 444
A42: 38 | B42: XMLComplete_BED_DAYS_BELOW_TT39 | C42: XMLComplete | D42: Tổng ngày giường nhỏ hơn hướng dẫn TT39 | E42: Không | F42: Có | G42: 454 | H42: =G42/23967 -> 0.018942713 | I42: Tổng ngày giường khai 9 nhỏ hơn số ngày điều trị theo TT39 11 (chênh 2). | J42: Nghiệp vụ | K42: Nghiệp vụ – Quy định BHYT | L42: Phòng BHYT | M42: CNTT; Phòng TCKT | N42: Sửa cách HIS tính ngày giường theo TT39 / thanh toán PT lần 2 trong ngày | P42: 473
A43: 39 | B43: XML3_EXECUTION_TIME_TOO_LONG | C43: XML3 | D43: Thời gian thực hiện dịch vụ dài bất thường | E43: Không | F43: Có | G43: 438 | H43: =G43/23967 -> 0.018275128 | I43: Dịch vụ 01.0175.0196 (08/09/2026 11:00 - 08/09/2041 15:00) kéo dài 131500 giờ 0 phút, vượt ngưỡng 24 giờ. Kiểm tra lại NGAY_TH_YL / NGAY_KQ. | J43: Kỹ thuật | K43: Kỹ thuật – HIS | L43: CNTT | M43: Khoa lâm sàng; Khoa thăm dò chức năng | N43: Lấy giờ bắt đầu/kết thúc thật; rà các dòng PTTT/DVKT kéo dài bất thường (cảnh báo, quy tắc mới 15/10) | O43: #33 | P43: 410
A44: 40 | B44: XML4_INFO_ERROR_KET_LUAN_EMPTY | C44: XML4 | D44: Kết luận không được để trống | E44: Có | F44: Có | G44: 432 | H44: =G44/23967 -> 0.018024784 | I44: Kết luận không được để trống đối với DVKT: 19.0222.0050.K.01916 | J44: Kỹ thuật | K44: Kỹ thuật – Tích hợp HIS–PACS | L44: CNTT | M44: Hãng PACS; Khoa CĐHA; Khoa Y học hạt nhân | N44: PACS/RIS trả đủ mô tả và kết luận; khoa CĐHA không duyệt kết quả trống | O44: #40 | P44: 418
A45: 41 | B45: XML1_SPECIAL_INPATIENT_ERROR_MA_LY_DO_VNT | C45: XML1 | D45: Thiếu mã lý do vào nội trú | E45: Không | F45: Có | G45: 425 | H45: =G45/23967 -> 0.017732716 | I45: Mã lý do vào nội trú không được để trống | J45: Nghiệp vụ | K45: Nghiệp vụ – Chuyên môn lâm sàng | L45: Khoa lâm sàng | M45: Phòng KHTH | N45: Bác sĩ nhập đủ, đúng nội dung chuyên môn trên HIS; Phòng KHTH kiểm tra | O45: #6 | P45: 410
A46: 42 | B46: XML1_ADMIN_INFO_ERROR_SO_CCCD | C46: XML1 | D46: Thiếu số CCCD/Định danh cá nhân | E46: Không | F46: Có | G46: 420 | H46: =G46/23967 -> 0.017524096 | I46: Số CCCD/định danh cá nhân không được để trống | J46: Nghiệp vụ | K46: Nghiệp vụ – Hành chính, tiếp đón | L46: Tiếp đón | M46: CNTT | N46: Tiếp đón nhập đủ thông tin hành chính; HIS bắt buộc trường bắt buộc | P46: 388
A47: 43 | B47: XML2_INVALID_DRUG_CODE | C47: XML2 | D47: Mã thuốc chưa có trong danh mục BHYT | E47: Có | F47: Có | G47: 396 | H47: =G47/23967 -> 0.016522719 | I47: Mã thuốc không có trong danh mục BHYT: 40.998 | J47: Nghiệp vụ | K47: Nghiệp vụ – Danh mục | L47: Khoa Dược | M47: Phòng BHYT; CNTT | N47: Khoa Dược đối chiếu danh mục thuốc trên HIS với danh mục được duyệt (mã, tên, hàm lượng, SĐK, thầu, đường dùng, dạng bào chế, ĐVT, giá) | O47: #18, #19 | P47: 367
A48: 44 | B48: XML3_DATE_MISMATCH | C48: XML3 | D48: Ngày y lệnh không khớp | E48: Có | F48: Có | G48: 368 | H48: =G48/23967 -> 0.015354446 | I48: Mã dịch vụ: 28.0027.0384; Không tìm thấy ngày y lệnh khớp với vật tư: N08.00.260.0092.155.0003 | J48: Nghiệp vụ | K48: Nghiệp vụ – Chuyên môn lâm sàng | L48: Khoa lâm sàng | M48: Phòng KHTH; CNTT | N48: Rà soát quy trình chỉ định – thực hiện; không gán giờ/người đồng loạt | P48: 358
A49: 45 | B49: XML14_INFO_ERROR_NGAY_HEN_KL_SMALLER_NGAY_RA | C49: XML14 | D49: Ngày hẹn khám lại nhỏ hơn hoặc bằng ngày ra | E49: Có | F49: Có | G49: 362 | H49: =G49/23967 -> 0.015104101 | I49: Ngày hẹn khám lại không được nhỏ hơn hoặc bằng ngày ra: 30/09/2026 <= 30/09/2026 15:17 | J49: Nghiệp vụ | K49: Nghiệp vụ – Chuyên môn lâm sàng | L49: Khoa lâm sàng | M49: Phòng KHTH | N49: Bác sĩ nhập đủ, đúng nội dung chuyên môn trên HIS; Phòng KHTH kiểm tra | O49: #59 | P49: 355
A50: 46 | B50: XML3_INVALID_APPROVED_DON_GIA_BH | C50: XML3 | D50: Giá DVKT cao hơn giá được phê duyệt | E50: Không | F50: Có | G50: 232 | H50: =G50/23967 -> 0.0096799766 | I50: Mã DVKT: 28.0467.1134; Có giá: 19616000; Giá phê duyệt nhỏ hơn: 4815700.00 | J50: Nghiệp vụ | K50: Nghiệp vụ – Danh mục | L50: Phòng TCKT | M50: Phòng KHTH; CNTT | N50: Đối chiếu bảng giá DVKT trên HIS với giá phê duyệt | P50: 194
A51: 47 | B51: XMLComplete_NGAY_TAI_KHAM_KHONG_KHOP_XML14 | C51: XMLComplete | D51: Ngày tái khám không có giấy hẹn khám lại tương ứng | E51: Không | F51: Có | G51: 194 | H51: =G51/23967 -> 0.0080944632 | I51: Hồ sơ hẹn tái khám ngày 20261223 nhưng không có giấy hẹn khám lại (XML14) | J51: Nghiệp vụ | K51: Nghiệp vụ – Chuyên môn lâm sàng | L51: Khoa lâm sàng | M51: Phòng KHTH | N51: Bác sĩ nhập đủ, đúng nội dung chuyên môn trên HIS; Phòng KHTH kiểm tra | P51: 187
A52: 48 | B52: XML3_EXCEEDS_APPROVED_PRICE | C52: XML3 | D52: Giá vật tư cao hơn giá được phê duyệt | E52: Không | F52: Có | G52: 187 | H52: =G52/23967 -> 0.007802395 | I52: Mã VTYT: N08.00.260; Có giá: 6250000; Giá phê duyệt: 5600000.00 | J52: Nghiệp vụ | K52: Nghiệp vụ – Danh mục | L52: Phòng VT-TBYT | M52: Phòng BHYT; CNTT | N52: Đối chiếu danh mục VTYT trên HIS với danh mục được duyệt theo thầu | P52: 177
A53: 49 | B53: XML3_INVALID_DEPARTMENT_CODE | C53: XML3 | D53: Khoa chỉ định giường không đúng quy định | E53: Không | F53: Có | G53: 159 | H53: =G53/23967 -> 0.0066341219 | I53: Khoa chỉ định: K103436 (liên khoa K10, K34, K36); Mã giường: K33.GBN.1 — khoa của giường không thuộc khoa chỉ định | J53: Nghiệp vụ | K53: Nghiệp vụ – Quy định BHYT | L53: Phòng BHYT | M53: Khoa lâm sàng; CNTT | N53: Khoa chỉ định giường phải đúng khoa của giường (trừ liên chuyên khoa) | P53: 157
A54: 50 | B54: XML2_INVALID_TT_THAU | C54: XML2 | D54: Mã thuốc sai thông tin thầu trong danh mục BHYT | E54: Không | F54: Có | G54: 87 | H54: =G54/23967 -> 0.0036299912 | I54: Mã thuốc: 40.981; Sai TT_THAU: KQ2500018490_2503131829;G2;N1;2025 | J54: Nghiệp vụ | K54: Nghiệp vụ – Danh mục | L54: Khoa Dược | M54: Phòng BHYT; CNTT | N54: Khoa Dược đối chiếu danh mục thuốc trên HIS với danh mục được duyệt (mã, tên, hàm lượng, SĐK, thầu, đường dùng, dạng bào chế, ĐVT, giá) | P54: 85
A55: 51 | B55: XMLComplete_THUOC_DVKT_ME_KHONG_KHOP | C55: XMLComplete | D55: Thuốc gắn DVKT mẹ không được BHYT thanh toán | E55: Có | F55: Có | G55: 82 | H55: =G55/23967 -> 0.0034213711 | I55: Iopamiro gắn DVKT 18.0191.0040: DVKT 18.0191.0040 Chụp cắt lớp vi tính lồng ngực không tiêm thuốc cản quang (từ 1- 32 dãy) (PACS) không thuộc danh sách DVKT mẹ hợp lệ của vật phẩm. Hợp lệ: 18.0133.0019 Chụp Xquang đường mật qua Kehr; 18.0150.0041 Chụp CLVT … | J55: Nghiệp vụ | K55: Nghiệp vụ – Quy định BHYT | L55: Phòng BHYT | M55: Khoa lâm sàng; CNTT | N55: Khai thuốc/VTYT kèm đúng DVKT mẹ (MA_DICH_VU, GOI_VTYT) theo danh mục vật phẩm kèm DVKT; rà soát danh mục ở màn quản trị "Vật phẩm kèm DVKT" | P55: 78
A56: 52 | B56: XML3_INFO_ERROR_PP_VO_CAM_EMPTY | C56: XML3 | D56: Thiếu phương pháp vô cảm | E56: Có | F56: Có | G56: 75 | H56: =G56/23967 -> 0.0031293028 | I56: Phương pháp vô cảm không được để trống đối với dịch vụ: Điều trị tủy răng và hàn kín hệ thống ống tủy bằng Gutta percha nguội có sử dụng trâm xoay máy [răng số 1, 2, 3] | J56: Nghiệp vụ | K56: Nghiệp vụ – Chuyên môn lâm sàng | L56: Khoa lâm sàng | M56: Phòng KHTH | N56: Bác sĩ nhập đủ, đúng nội dung chuyên môn trên HIS; Phòng KHTH kiểm tra | O56: #34 | P56: 78
A57: 53 | B57: XML3_INVALID_MA_DICH_VU_NGAY_VAO | C57: XML3 | D57: Không tìm thấy dịch vụ hợp lệ | E57: Có | F57: Có | G57: 67 | H57: =G57/23967 -> 0.0027955105 | I57: Không tìm thấy dịch vụ hợp lệ cho mã dịch vụ: 24.0184.1637 với ngày vào: 07/10/2023 14:19 | J57: Nghiệp vụ | K57: Nghiệp vụ – Danh mục | L57: Phòng KHTH | M57: Phòng BHYT; CNTT | N57: Nhập đủ danh mục DVKT đã được BHXH phê duyệt (cơ sở 01929 chỉ có 8.123 dòng so với 15.660 của 37470); tên DVKT trên HIS theo đúng tên phê duyệt | P57: 1
A58: 54 | B58: XML1_WARNING_MA_BENH_KT | C58: XML1 | D58: Mã bệnh kèm theo thuộc nhóm bệnh cảnh báo | E58: Có | F58: Có | G58: 66 | H58: =G58/23967 -> 0.0027537865 | I58: Mã bệnh kèm theo thuộc nhóm cảnh báo: Z00.4 (Z00) | J58: Nghiệp vụ | K58: Nghiệp vụ – Chuyên môn lâm sàng | L58: Khoa lâm sàng | M58: Phòng KHTH | N58: Bác sĩ nhập đủ, đúng nội dung chuyên môn trên HIS; Phòng KHTH kiểm tra | O58: #14 | P58: 65
A59: 55 | B59: XML3_T_BHTT_SAI_CONG_THUC | C59: XML3 | D59: Tiền BHYT thanh toán không đúng công thức | E59: Không | F59: Có | G59: 64 | H59: =G59/23967 -> 0.0026703384 | I59: T_BHTT = THANH_TIEN_BH x MUC_HUONG/100 = 9,912,800.00, hiện khai: 9,015,203.72 | J59: Kỹ thuật | K59: Kỹ thuật – HIS | L59: CNTT | M59: Phòng TCKT; Phòng BHYT | N59: Sửa công thức tính tiền/tỷ lệ/nguồn chi trả trên HIS | P59: 60
A60: 56 | B60: XML2_LIEU_DUNG_QUANTITY_MISMATCH | C60: XML2 | D60: Tổng lượng theo liều khác số lượng thanh toán | E60: Không | F60: Có | G60: 52 | H60: =G60/23967 -> 0.0021696499 | I60: Tổng lượng theo liều (95.004) cao hơn số lượng thanh toán (95). Thuốc: Đảng sâm | J60: Kỹ thuật | K60: Kỹ thuật – HIS | L60: CNTT | M60: Phòng KHTH; Khoa Dược | N60: Sửa ánh xạ/định dạng dữ liệu khi HIS xuất XML; bắt buộc nhập trường còn thiếu | P60: 52
A61: 57 | B61: XMLComplete_DVKT_THIEU_VAT_PHAM_KEM | C61: XMLComplete | D61: DVKT bắt buộc kèm vật phẩm nhưng không có vật phẩm | E61: Không | F61: Có | G61: 52 | H61: =G61/23967 -> 0.0021696499 | I61: 18.0219.0041 Chụp cắt lớp vi tính tầng trên ổ bụng thường quy (gồm: chụp Cắt lớp vi tính gan - mật, tụy, lách, dạ dày - tá tràng.v.v.) (từ 1-32 dãy) (PACS) BHYT trả 522.960đ, YL 09/10/2026: hồ sơ không có vật phẩm đi kèm (cần một trong: Xenetix 300, Omnipaq… | J61: Nghiệp vụ | K61: Nghiệp vụ – Quy định BHYT | L61: Phòng BHYT | M61: Khoa lâm sàng; CNTT | N61: Khai thuốc/VTYT kèm đúng DVKT mẹ (MA_DICH_VU, GOI_VTYT) theo danh mục vật phẩm kèm DVKT; rà soát danh mục ở màn quản trị "Vật phẩm kèm DVKT" | P61: 49
A62: 58 | B62: XMLComplete_INVALID_BED_DAYS | C62: XMLComplete | D62: Thanh toán ngày giường sai quy định (trừ trường hợp đặc biệt) | E62: Không | F62: Có | G62: 34 | H62: =G62/23967 -> 0.0014186173 | I62: Tổng ngày giường khai 9.5 lớn hơn số ngày giường đúng theo TT39 9, thừa 0.5. | J62: Nghiệp vụ | K62: Nghiệp vụ – Quy định BHYT | L62: Phòng BHYT | M62: Khoa lâm sàng; CNTT | N62: Rà soát chỉ định ngày giường, công khám, khoa chỉ định đúng quy định BHYT | P62: 39
A63: 59 | B63: XMLComplete_SECOND_SURGERY_FULL_PAYMENT | C63: XMLComplete | D63: Phẫu thuật lần 2 trong ngày thanh toán 100% | E63: Có | F63: Có | G63: 31 | H63: =G63/23967 -> 0.0012934452 | I63: Phẫu thuật lần 7 ngày 20260930 (dịch vụ 03.2508.1049) thanh toán 100% | J63: Nghiệp vụ | K63: Nghiệp vụ – Quy định BHYT | L63: Phòng BHYT | M63: CNTT; Phòng TCKT | N63: Sửa cách HIS tính ngày giường theo TT39 / thanh toán PT lần 2 trong ngày | P63: 53
A64: 60 | B64: XML3_INVALID_TT_THAU_FORMAT | C64: XML3 | D64: Thông tin thầu không đúng định dạng | E64: Có | F64: Có | G64: 29 | H64: =G64/23967 -> 0.0012099971 | I64: Mã vật tư: N08.00.010.3330.213.0004; có TT_THAU không đúng định dạng: 866/QĐ-BM;;N0;2026 | J64: Nghiệp vụ | K64: Nghiệp vụ – Danh mục | L64: Phòng VT-TBYT | M64: Phòng BHYT; CNTT | N64: Đối chiếu danh mục VTYT trên HIS với danh mục được duyệt theo thầu | P64: 29
A65: 61 | B65: XML11_INFO_ERROR_PP_DIEUTRI | C65: XML11 | D65: Thiếu phương pháp điều trị | E65: Có | F65: Có | G65: 20 | H65: =G65/23967 -> 0.00083448074 | I65: Phương pháp điều trị không được để trống | J65: Nghiệp vụ | K65: Nghiệp vụ – Chuyên môn lâm sàng | L65: Khoa lâm sàng | M65: Phòng KHTH | N65: Bác sĩ nhập đủ, đúng nội dung chuyên môn trên HIS; Phòng KHTH kiểm tra | O65: #52 | P65: 19
A66: 62 | B66: XML3_MEDICAL_SUPPLY_NOT_IN_CATALOG | C66: XML3 | D66: VTYT nằm ngoài danh mục BHYT | E66: Không | F66: Có | G66: 20 | H66: =G66/23967 -> 0.00083448074 | I66: VTYT có mã: với TT_THAU: 6365/QĐ-BM;G0;N0;2026 không có trong danh mục BHYT | J66: Nghiệp vụ | K66: Nghiệp vụ – Danh mục | L66: Phòng VT-TBYT | M66: Phòng BHYT; CNTT | N66: Đối chiếu danh mục VTYT trên HIS với danh mục được duyệt theo thầu | P66: 18
A67: 63 | B67: XML8_INFO_ERROR_TOMTAT_KQ | C67: XML8 | D67: Thiếu tóm tắt kết quả | E67: Có | F67: Có | G67: 19 | H67: =G67/23967 -> 0.00079275671 | I67: Tóm tắt kết quả không được để trống | J67: Nghiệp vụ | K67: Nghiệp vụ – Chuyên môn lâm sàng | L67: Khoa lâm sàng | M67: Phòng KHTH | N67: Bác sĩ nhập đủ, đúng nội dung chuyên môn trên HIS; Phòng KHTH kiểm tra | O67: #47 | P67: 19
A68: 64 | B68: XML1_ADMIN_INFO_ERROR_MA_NOI_DI_NOT_FOUND | C68: XML1 | D68: Mã nơi đi không có trong danh mục | E68: Có | F68: Có | G68: 16 | H68: =G68/23967 -> 0.0006675846 | I68: Mã nơi đi: 79472 không có trong danh mục CSKCB | J68: Nghiệp vụ | K68: Nghiệp vụ – Hành chính, tiếp đón | L68: Tiếp đón | M68: Phòng BHYT | N68: Nhập đúng mã cơ sở KCB nơi đi/đến/ĐKBĐ (có mã gõ sai như 38230b) | P68: 16
A69: 65 | B69: XMLComplete_THUOC_KHONG_CO_DVKT_ME | C69: XMLComplete | D69: Thuốc thanh toán ngoài giá không có DVKT mẹ được BHYT thanh toán | E69: Có | F69: Có | G69: 15 | H69: =G69/23967 -> 0.00062586056 | I69: Omnipaque (40.644) BHYT trả 353.609đ, YL 05/10/2026: không có DVKT mẹ trong hồ sơ. Cần một trong: 18.0150.0041 Chụp CLVT sọ não có tiêm thuốc cản quang (từ 1-32 dãy) [không in phim]; 18.0156.0041 Chụp CLVT hàm - mặt có tiêm thuốc cản quang (từ 1-32 dãy) [kh… | J69: Nghiệp vụ | K69: Nghiệp vụ – Quy định BHYT | L69: Phòng BHYT | M69: Khoa lâm sàng; CNTT | N69: Khai thuốc/VTYT kèm đúng DVKT mẹ (MA_DICH_VU, GOI_VTYT) theo danh mục vật phẩm kèm DVKT; rà soát danh mục ở màn quản trị "Vật phẩm kèm DVKT" | P69: 14
A70: 66 | B70: XML2_LIEU_DUNG_INVALID_FORMAT | C70: XML2 | D70: Liều dùng không đúng định dạng 130 | E70: Có | F70: Có | G70: 11 | H70: =G70/23967 -> 0.00045896441 | I70: Liều dùng "Đặt hậu môn khi đau nhiều * 1 ngày [1,0 Viên/ngày]" của thuốc Voltaren không đúng định dạng 130 (SL/lần * số lần/ngày * số ngày) | J70: Kỹ thuật | K70: Kỹ thuật – HIS | L70: CNTT | M70: Phòng KHTH; Khoa Dược | N70: Sửa ánh xạ/định dạng dữ liệu khi HIS xuất XML; bắt buộc nhập trường còn thiếu | P70: 11
A71: 67 | B71: XMLComplete_GOI_VTYT_KHONG_KHOP | C71: XMLComplete | D71: Gói VTYT không khớp DVKT mẹ được BHYT thanh toán | E71: Có | F71: Có | G71: 11 | H71: =G71/23967 -> 0.00045896441 | I71: Kẹp vá sọ não tự tiêu 2 phía CRANIOFIX-ABSORBABLE gắn DVKT 26.0003.0379: DVKT 26.0003.0379 Phẫu thuật vi phẫu u não đường giữa không thuộc danh sách DVKT mẹ hợp lệ của vật phẩm. Hợp lệ: 26.0004.0387 Phẫu thuật vi phẫu dị dạng mạch não; 28.0027.0384 Phẫu th… | J71: Nghiệp vụ | K71: Nghiệp vụ – Quy định BHYT | L71: Phòng BHYT | M71: Khoa lâm sàng; CNTT | N71: Khai thuốc/VTYT kèm đúng DVKT mẹ (MA_DICH_VU, GOI_VTYT) theo danh mục vật phẩm kèm DVKT; rà soát danh mục ở màn quản trị "Vật phẩm kèm DVKT" | P71: 3
A72: 68 | B72: XML2_PRESCRIPTION_EXCEEDS_30_DAYS | C72: XML2 | D72: Kê thuốc quá số ngày cho phép | E72: Có | F72: Có | G72: 10 | H72: =G72/23967 -> 0.00041724037 | I72: Kê 91 ngày (> 90). Thuốc: pms-Tenofovir | J72: Nghiệp vụ | K72: Nghiệp vụ – Chuyên môn lâm sàng | L72: Khoa lâm sàng | M72: Phòng KHTH | N72: Bác sĩ nhập đủ, đúng nội dung chuyên môn trên HIS; Phòng KHTH kiểm tra | P72: 10
A73: 69 | B73: XML1_ADMIN_INFO_ERROR_MAXA_CU_TRU_NOT_FOUND | C73: XML1 | D73: Mã phường xã không tồn tại | E73: Có | F73: Có | G73: 9 | H73: =G73/23967 -> 0.00037551633 | I73: Mã phường xã không tồn tại trong danh mục: 14032 | J73: Kỹ thuật | K73: Kỹ thuật – HIS | L73: CNTT | M73: Tiếp đón | N73: Cập nhật danh mục hành chính 2 cấp và danh mục nghề nghiệp trên HIS; khoá mã cũ | P73: 8
A74: 70 | B74: XML1_DOI_TUONG_KCB_THIEU_GIAY_CHUYEN_TUYEN | C74: XML1 | D74: Thiếu số phiếu chuyển cơ sở KCB hoặc số phiếu hẹn khám lại | E74: Có | F74: Có | G74: 8 | H74: =G74/23967 -> 0.0003337923 | I74: Mã đối tượng 1.5 (Đến KCB theo phiếu hẹn khám lại) nhưng GIAY_CHUYEN_TUYEN để trống | J74: Nghiệp vụ | K74: Nghiệp vụ – Quy định BHYT | L74: Phòng BHYT | M74: Tiếp đón; CNTT | N74: Tiếp đón khai đúng mã đối tượng, giấy chuyển tuyến/hẹn, mức hưởng theo thẻ; HIS chặn khi thiếu | O74: #17 | P74: 6
A75: 71 | B75: XML3_NGAY_KQ_GREATER_NGAY_RA | C75: XML3 | D75: Ngày kết quả dịch vụ lớn hơn ngày ra viện | E75: Không | F75: Có | G75: 8 | H75: =G75/23967 -> 0.0003337923 | I75: Ngày KQ (30/10/2026 20:15) > ngày ra (02/10/2026 10:06). Dịch vụ: Thay huyết tương sử dụng huyết tương | J75: Kỹ thuật | K75: Kỹ thuật – Tích hợp HIS–PACS/LIS | L75: CNTT | M75: Khoa CĐHA; Khoa Xét nghiệm | N75: Thống nhất một nguồn thời gian trả kết quả giữa PACS/LIS và HIS; rà ca trả kết quả sau ra viện | O75: #32 | P75: 2
A76: 72 | B76: XML1_SPECIAL_INPATIENT_ERROR_PP_DIEU_TRI | C76: XML1 | D76: Thiếu phương pháp điều trị | E76: Có | F76: Có | G76: 7 | H76: =G76/23967 -> 0.00029206826 | I76: Phương pháp điều trị không được để trống | J76: Nghiệp vụ | K76: Nghiệp vụ – Chuyên môn lâm sàng | L76: Khoa lâm sàng | M76: Phòng KHTH | N76: Bác sĩ nhập đủ, đúng nội dung chuyên môn trên HIS; Phòng KHTH kiểm tra | O76: #16 | P76: 6
A77: 73 | B77: XML1_ADMIN_INFO_ERROR_TO_MUCH_CAN_NANG | C77: XML1 | D77: Cân nặng không hợp lệ | E77: Không | F77: Có | G77: 6 | H77: =G77/23967 -> 0.00025034422 | I77: Cân nặng không hợp lệ: 850 | J77: Nghiệp vụ | K77: Nghiệp vụ – Hành chính, tiếp đón | L77: Tiếp đón | M77: CNTT | N77: Tiếp đón nhập đủ thông tin hành chính; HIS bắt buộc trường bắt buộc | O77: #10 | P77: 7
A78: 74 | B78: XMLComplete_EXCESS_BED_DAYS | C78: XMLComplete | D78: Điều trị nội trú >= 4h và <= 24h tính thừa ngày giường | E78: Không | F78: Có | G78: 6 | H78: =G78/23967 -> 0.00025034422 | I78: Thời gian điều trị nội trú từ 4 đến 24 giờ, tính thừa ngày giường: 2 | J78: Nghiệp vụ | K78: Nghiệp vụ – Quy định BHYT | L78: Phòng BHYT | M78: Khoa lâm sàng; CNTT | N78: Rà soát chỉ định ngày giường, công khám, khoa chỉ định đúng quy định BHYT | P78: 6
A79: 75 | B79: XML1_ADMIN_INFO_ERROR_MATINH_CU_TRU_NOT_FOUND | C79: XML1 | D79: Mã tỉnh không tồn tại | E79: Có | F79: Có | G79: 6 | H79: =G79/23967 -> 0.00025034422 | I79: Mã tỉnh không tồn tại trong danh mục: 001 | J79: Kỹ thuật | K79: Kỹ thuật – HIS | L79: CNTT | M79: Tiếp đón | N79: Cập nhật danh mục hành chính 2 cấp và danh mục nghề nghiệp trên HIS; khoá mã cũ | O79: #3 | P79: 5
A80: 76 | B80: XML9_INFO_ERROR_INVALID_MA_THE_TAM | C80: XML9 | D80: Định dạng mã thẻ tạm không hợp lệ | E80: Có | F80: Có | G80: 6 | H80: =G80/23967 -> 0.00025034422 | I80: Mã thẻ tạm không đúng theo quy định: TR1010133072595 - Phần đầu tiên không phải là: TE1 | J80: Nghiệp vụ | K80: Nghiệp vụ – Quy định BHYT | L80: Phòng BHYT | M80: Tiếp đón; CNTT | N80: Tiếp đón khai đúng mã đối tượng, giấy chuyển tuyến/hẹn, mức hưởng theo thẻ; HIS chặn khi thiếu | P80: 5
A81: 77 | B81: XML1_DISEASE_ICD_CODE_ERROR_MA_BENH_KT | C81: XML1 | D81: Mã bệnh kèm theo không tồn tại | E81: Có | F81: Có | G81: 6 | H81: =G81/23967 -> 0.00025034422 | I81: Mã bệnh kèm theo không tồn tại trong danh mục ICD10: M32.1 | J81: Nghiệp vụ | K81: Nghiệp vụ – Chuyên môn lâm sàng | L81: Khoa lâm sàng | M81: Phòng KHTH | N81: Bác sĩ nhập đủ, đúng nội dung chuyên môn trên HIS; Phòng KHTH kiểm tra | O81: #12, #13 | P81: 4
A82: 78 | B82: XML1_ADMIN_INFO_ERROR_CHAN_DOAN_VAO | C82: XML1 | D82: Thiếu chẩn đoán vào | E82: Không | F82: Có | G82: 5 | H82: =G82/23967 -> 0.00020862019 | I82: Chẩn đoán vào không được để trống | J82: Nghiệp vụ | K82: Nghiệp vụ – Chuyên môn lâm sàng | L82: Khoa lâm sàng | M82: Phòng KHTH | N82: Bác sĩ nhập đủ, đúng nội dung chuyên môn trên HIS; Phòng KHTH kiểm tra | P82: 5
A83: 79 | B83: XML1_ADMIN_INFO_ERROR_MA_DKBD_NOT_FOUND | C83: XML1 | D83: Mã đăng ký ban đầu không có trong danh mục | E83: Không | F83: Có | G83: 5 | H83: =G83/23967 -> 0.00020862019 | I83: Mã đăng ký ban đầu: 38101 không có trong danh mục CSKCB | J83: Nghiệp vụ | K83: Nghiệp vụ – Hành chính, tiếp đón | L83: Tiếp đón | M83: Phòng BHYT | N83: Nhập đúng mã cơ sở KCB nơi đi/đến/ĐKBĐ (có mã gõ sai như 38230b) | P83: 5
A84: 80 | B84: XML1_DOI_TUONG_KCB_KHONG_PHAI_SO_SINH | C84: XML1 | D84: Không phải đối tượng trẻ sơ sinh phải điều trị ngay sau khi sinh ra | E84: Có | F84: Có | G84: 4 | H84: =G84/23967 -> 0.00016689615 | I84: Mã đối tượng 1.7 (Trẻ sơ sinh phải điều trị ngay sau khi sinh ra) nhưng người bệnh sinh ngày 23/09/1989, đã 13.528 ngày tuổi khi vào viện (tối đa 28 ngày) | J84: Nghiệp vụ | K84: Nghiệp vụ – Quy định BHYT | L84: Phòng BHYT | M84: Tiếp đón; CNTT | N84: Tiếp đón khai đúng mã đối tượng, giấy chuyển tuyến/hẹn, mức hưởng theo thẻ; HIS chặn khi thiếu | P84: 4
A85: 81 | B85: XML9_INFO_ERROR_MA_BHXH_NND | C85: XML9 | D85: Thiếu mã BHXH Người nuôi dưỡng | E85: Có | F85: Có | G85: 4 | H85: =G85/23967 -> 0.00016689615 | I85: Mã BHXH người nuôi dưỡng không được để trống | J85: Nghiệp vụ | K85: Nghiệp vụ – Quy định BHYT | L85: Phòng BHYT | M85: Tiếp đón; CNTT | N85: Tiếp đón khai đúng mã đối tượng, giấy chuyển tuyến/hẹn, mức hưởng theo thẻ; HIS chặn khi thiếu | P85: 4
A86: 82 | B86: XML9_INFO_ERROR_MA_THE_BHYT_NND_LENGTH | C86: XML9 | D86: Mã thẻ BHYT Người nuôi dưỡng không hợp lệ | E86: Có | F86: Có | G86: 4 | H86: =G86/23967 -> 0.00016689615 | I86: Mã thẻ BHYT Người nuôi dưỡng phải có độ dài là 15 ký tự: HC437035187005171 | J86: Nghiệp vụ | K86: Nghiệp vụ – Quy định BHYT | L86: Phòng BHYT | M86: Tiếp đón; CNTT | N86: Tiếp đón khai đúng mã đối tượng, giấy chuyển tuyến/hẹn, mức hưởng theo thẻ; HIS chặn khi thiếu | P86: 4
A87: 83 | B87: XMLComplete_VTYT_KHONG_CO_DVKT_ME | C87: XMLComplete | D87: XMLComplete_VTYT_KHONG_CO_DVKT_ME | E87: Có | F87: Có | G87: 4 | H87: =G87/23967 -> 0.00016689615 | I87: Prismaflex M100 set (N07.02.060.2181.240.0001) BHYT trả 5.840.000đ, YL 10/09/2026: không có DVKT mẹ trong hồ sơ. Cần một trong: 01.0181.0118 Lọc máu thẩm tách liên tục cấp cứu (CVVHDF); 01.0176.0118 Lọc máu liên tục cấp cứu (CVVH); 01.0182.0118 Lọc máu thẩm… | J87: Nghiệp vụ | K87: Nghiệp vụ – Quy định BHYT | L87: Phòng BHYT | M87: Khoa lâm sàng; CNTT | N87: Khai thuốc/VTYT kèm đúng DVKT mẹ (MA_DICH_VU, GOI_VTYT) theo danh mục vật phẩm kèm DVKT; rà soát danh mục ở màn quản trị "Vật phẩm kèm DVKT" | P87: 4
A88: 84 | B88: XML3_INFO_ERROR_GOI_THAU | C88: XML3 | D88: Gói thầu không đúng định dạng | E88: Có | F88: Có | G88: 3 | H88: =G88/23967 -> 0.00012517211 | I88: Gói thầu của dịch vụ: Quả lọc hấp phụ sử dụng trong chống độc MG250; không đúng định dạng: 1224/QĐ-BM;;N0;2024 | J88: Nghiệp vụ | K88: Nghiệp vụ – Danh mục | L88: Phòng VT-TBYT | M88: Phòng BHYT; CNTT | N88: Đối chiếu danh mục VTYT trên HIS với danh mục được duyệt theo thầu | P88: 3
A89: 85 | B89: XMLComplete_SHORT_INPATIENT_STAY | C89: XMLComplete | D89: Điều trị nội trú < 4h không được tính tiền giường | E89: Không | F89: Có | G89: 3 | H89: =G89/23967 -> 0.00012517211 | I89: Thời gian điều trị nội trú nhỏ hơn 4 giờ, không được tính tiền giường. | J89: Nghiệp vụ | K89: Nghiệp vụ – Quy định BHYT | L89: Phòng BHYT | M89: Khoa lâm sàng; CNTT | N89: Rà soát chỉ định ngày giường, công khám, khoa chỉ định đúng quy định BHYT | P89: 3
A90: 86 | B90: XMLComplete_DUPLICATE_EXAMINATION_SERVICE | C90: XMLComplete | D90: Trùng dịch vụ khám bệnh | E90: Không | F90: Có | G90: 3 | H90: =G90/23967 -> 0.00012517211 | I90: Mỗi dịch vụ khám chỉ được tính 1 lần. Dịch vụ khám bị lặp: 10.22 | J90: Nghiệp vụ | K90: Nghiệp vụ – Quy định BHYT | L90: Phòng BHYT | M90: Khoa lâm sàng; CNTT | N90: Rà soát chỉ định ngày giường, công khám, khoa chỉ định đúng quy định BHYT | P90: 2
A91: 87 | B91: XML11_INFO_ERROR_DEN_NGAY | C91: XML11 | D91: Thiếu đến ngày | E91: Có | F91: Có | G91: 2 | H91: =G91/23967 -> 8.3448074e-05 | I91: Đến ngày không được để trống | J91: Nghiệp vụ | K91: Nghiệp vụ – Chuyên môn lâm sàng | L91: Khoa lâm sàng | M91: Phòng KHTH | N91: Bác sĩ nhập đủ, đúng nội dung chuyên môn trên HIS; Phòng KHTH kiểm tra | P91: 2
A92: 88 | B92: XML11_INFO_ERROR_SO_NGAY_NGHI | C92: XML11 | D92: Thiếu số ngày nghỉ | E92: Có | F92: Có | G92: 2 | H92: =G92/23967 -> 8.3448074e-05 | I92: Số ngày nghỉ không được để trống | J92: Nghiệp vụ | K92: Nghiệp vụ – Chuyên môn lâm sàng | L92: Khoa lâm sàng | M92: Phòng KHTH | N92: Bác sĩ nhập đủ, đúng nội dung chuyên môn trên HIS; Phòng KHTH kiểm tra | P92: 2
A93: 89 | B93: XML11_INFO_ERROR_TU_NGAY | C93: XML11 | D93: Thiếu từ ngày | E93: Có | F93: Có | G93: 2 | H93: =G93/23967 -> 8.3448074e-05 | I93: Từ ngày không được để trống | J93: Nghiệp vụ | K93: Nghiệp vụ – Chuyên môn lâm sàng | L93: Khoa lâm sàng | M93: Phòng KHTH | N93: Bác sĩ nhập đủ, đúng nội dung chuyên môn trên HIS; Phòng KHTH kiểm tra | P93: 2
... A97: 93 | B97: XML1_DOI_TUONG_KCB_TU_DEN_CO_NOI_DI | C97: XML1 | D97: Người bệnh tự đến nhưng lại có mã nơi chuyển đi | E97: Có | F97: Có | G97: 2 | H97: =G97/23967 -> 8.3448074e-05 | I97: Mã đối tượng 3.6 (Dân tộc thiểu số, hộ nghèo vùng khó khăn đến KCB nội trú tại cơ sở cấp chuyên sâu) nhưng MA_NOI_DI = | J97: Nghiệp vụ | K97: Nghiệp vụ – Quy định BHYT | L97: Phòng BHYT | M97: Tiếp đón; CNTT | N97: Tiếp đón khai đúng mã đối tượng, giấy chuyển tuyến/hẹn, mức hưởng theo thẻ; HIS chặn khi thiếu | P97: 2
A98: 94 | B98: XML1_WARNING_MA_BENH_CHINH | C98: XML1 | D98: Mã bệnh chính thuộc nhóm bệnh cảnh báo | E98: Có | F98: Có | G98: 2 | H98: =G98/23967 -> 8.3448074e-05 | I98: Mã bệnh chính: Z00.4 thuộc nhóm cảnh báo (Z00) | J98: Nghiệp vụ | K98: Nghiệp vụ – Chuyên môn lâm sàng | L98: Khoa lâm sàng | M98: Phòng KHTH | N98: Bác sĩ nhập đủ, đúng nội dung chuyên môn trên HIS; Phòng KHTH kiểm tra | O98: #14 | P98: 2
A99: 95 | B99: XML3_INVALID_ORDER_TIME | C99: XML3 | D99: Thời gian chỉ định không hợp lệ | E99: Có | F99: Có | G99: 2 | H99: =G99/23967 -> 8.3448074e-05 | I99: Thời gian y lệnh không nằm trong khoảng thời gian vào (25/09/2026 12:17) và ra (07/10/2026 13:42) | J99: Nghiệp vụ | K99: Nghiệp vụ – Chuyên môn lâm sàng | L99: Khoa lâm sàng | M99: Phòng KHTH; CNTT | N99: Rà soát quy trình chỉ định – thực hiện; không gán giờ/người đồng loạt | O99: #30 | P99: 2
A100: 96 | B100: XML3_OUTPATIENT_BED_DAY_ERROR | C100: XML3 | D100: Mã loại KCB không được chỉ định ngày giường | E100: Có | F100: Có | G100: 2 | H100: =G100/23967 -> 8.3448074e-05 | I100: MA_LOAI_KCB là (Khám hoặc Điều trị ngoại trú) nhưng có chỉ định dịch vụ ngày giường | J100: Nghiệp vụ | K100: Nghiệp vụ – Quy định BHYT | L100: Phòng BHYT | M100: Khoa lâm sàng; CNTT | N100: Rà soát chỉ định ngày giường, công khám, khoa chỉ định đúng quy định BHYT | P100: 2
A101: 97 | B101: XML13_INFO_ERROR_MA_BENH_KT_NOT_FOUND | C101: XML13 | D101: Mã bệnh kèm theo không tồn tại | E101: Có | F101: Có | G101: 2 | H101: =G101/23967 -> 8.3448074e-05 | I101: Mã bệnh kèm theo không tồn tại trong danh mục ICD10: | J101: Nghiệp vụ | K101: Nghiệp vụ – Chuyên môn lâm sàng | L101: Khoa lâm sàng | M101: Phòng KHTH | N101: Bác sĩ nhập đủ, đúng nội dung chuyên môn trên HIS; Phòng KHTH kiểm tra | O101: #54 | P101: 1
A102: 98 | B102: XML1_ADMIN_INFO_ERROR_MA_DOITUONG_KCB_INVALID | C102: XML1 | D102: Mã đối tượng KCB không hợp lệ | E102: Có | F102: Có | G102: 2 | H102: =G102/23967 -> 8.3448074e-05 | I102: Mã đối tượng KCB Trái tuyến nhưng thẻ BHYT Đúng tuyến | J102: Nghiệp vụ | K102: Nghiệp vụ – Quy định BHYT | L102: Phòng BHYT | M102: Tiếp đón; CNTT | N102: Tiếp đón khai đúng mã đối tượng, giấy chuyển tuyến/hẹn, mức hưởng theo thẻ; HIS chặn khi thiếu | P102: 1
A103: 99 | B103: XML1_ADMIN_INFO_ERROR_MA_DANTOC | C103: XML1 | D103: Thiếu mã dân tộc | E103: Có | F103: Có | G103: 1 | H103: =G103/23967 -> 4.1724037e-05 | I103: Mã dân tộc không được để trống | J103: Nghiệp vụ | K103: Nghiệp vụ – Hành chính, tiếp đón | L103: Tiếp đón | M103: CNTT | N103: Tiếp đón nhập đủ thông tin hành chính; HIS bắt buộc trường bắt buộc | P103: 20
A104: 100 | B104: XML11_INFO_ERROR_MA_THE_BHYT_LENGTH | C104: XML11 | D104: Mã thẻ BHYT không hợp lệ | E104: Có | F104: Có | G104: 1 | H104: =G104/23967 -> 4.1724037e-05 | I104: Mã thẻ BHYT phải có độ dài là 15 ký tự: DN431031071005275 | J104: Nghiệp vụ | K104: Nghiệp vụ – Quy định BHYT | L104: Phòng BHYT | M104: Tiếp đón; CNTT | N104: Tiếp đón khai đúng mã đối tượng, giấy chuyển tuyến/hẹn, mức hưởng theo thẻ; HIS chặn khi thiếu | P104: 1
...

Sheet Đối chiếu FIXERROR
A1: ĐỐI CHIẾU: LỖI HỆ THỐNG KHÁC TỰ SỬA (FIXERROR) ↔ LỖI TIỀN GIÁM ĐỊNH CHẶN
A2: Nguồn quy tắc: fixerror-he-thong-khac-lech-his-cong.xlsx. Tiền giám định không tự sửa – chặn/cảnh báo để sửa tại nguồn.
A4: # | B4: Bảng | C4: Trường bị sửa | D4: FIXERROR tự sửa thế nào | E4: Mức độ (FIXERROR) | F4: Mã lỗi Tiền giám định tương ứng | G4: Số HS Tiền giám định bắt (mã lớn nhất) | H4: Nhóm lỗi | I4: Đơn vị sửa tại nguồn | J4: Còn dùng | K4: Ghi chú | N4: 18
A5: 1 | B5: XML1 | C5: MA_KHUVUC | D5: Xoá thành rỗng | E5: Trung bình | F5: XML1_ADMIN_INFO_ERROR_MA_KHUVUC XML1_DOI_TUONG_KCB_THIEU_MA_KHUVUC | G5: 0 | H5: Nghiệp vụ – Quy định BHYT | I5: Phòng BHYT | K5: Không dùng | M5: =59-21 -> 38
A6: 2 | B6: XML1 | C6: MATINH_CU_TRU | D6: Gán cứng "01" (Hà Nội) | E6: Cao | F6: XML1_ADMIN_INFO_ERROR_MATINH_CU_TRU | G6: 0 | H6: Nghiệp vụ – Hành chính, tiếp đón | I6: Tiếp đón | K6: Không dùng
A7: 3 | B7: XML1 | C7: MATINH_CU_TRU | D7: Lấy ký tự thứ 2–3 (Substring(1,2)) | E7: Trung bình | F7: XML1_ADMIN_INFO_ERROR_MATINH_CU_TRU_NOT_FOUND | G7: 6 | H7: Kỹ thuật – HIS | I7: CNTT | K7: Không dùng
A8: 4 | B8: XML1 | C8: DIA_CHI | D8: Ghép ".,<xã>,<huyện>,<tỉnh>" từ danh mục ĐVHC; không khớp thì ra ".,,," | E8: Cao | F8: Chưa có quy tắc tương ứng | K8: Không dùng
A9: 5 | B9: XML1 | C9: LY_DO_VV | D9: Gán chữ "LY_DO_VV" | E9: Cao | F9: XML1_ADMIN_INFO_ERROR_LY_DO_VV | G9: 1 | H9: Nghiệp vụ – Chuyên môn lâm sàng | I9: Khoa lâm sàng | K9: Không rõ
A10: 6 | B10: XML1 | C10: LY_DO_VNT | D10: Ghi đè LY_DO_VNT bằng 5 ký tự đầu của MA_BENH_CHINH | E10: Cao | F10: XML1_SPECIAL_INPATIENT_ERROR_MA_LY_DO_VNT | G10: 425 | H10: Nghiệp vụ – Chuyên môn lâm sàng | I10: Khoa lâm sàng | K10: Không rõ
A11: 7 | B11: XML1 | C11: LY_DO_VNT | D11: Gán chữ "LY_DO_VNT" | E11: Cao | F11: XML1_SPECIAL_INPATIENT_ERROR_LY_DO_VNT | G11: 0 | H11: Nghiệp vụ – Chuyên môn lâm sàng | I11: Khoa lâm sàng | K11: Không rõ
A12: 8 | B12: XML1 | C12: MA_NGHE_NGHIEP | D12: Gán "00" | E12: Trung bình | F12: XML1_ADMIN_INFO_ERROR_MA_NGHE_NGHIEP | G12: 0 | H12: Nghiệp vụ – Hành chính, tiếp đón | I12: Tiếp đón | K12: Không dùng
A13: 9 | B13: XML1 | C13: CAN_NANG | D13: Bịa cân nặng theo tuổi: ≤1 tuổi = 5 kg; 2 tuổi = 13; 3 = 14 … 17 tuổi = 40; ≥18 tuổi = 45 kg | E13: Nghiêm trọng | F13: XML1_ADMIN_INFO_ERROR_CAN_NANG | G13: 0 | H13: Nghiệp vụ – Hành chính, tiếp đón | I13: Tiếp đón | K13: Không rõ
A14: 10 | B14: XML1 | C14: CAN_NANG | D14: Chia 1000 (giả định nhập gam) | E14: Trung bình | F14: XML1_ADMIN_INFO_ERROR_TO_MUCH_CAN_NANG | G14: 6 | H14: Nghiệp vụ – Hành chính, tiếp đón | I14: Tiếp đón | K14: Không rõ
A15: 11 | B15: XML1 | C15: CAN_NANG_CON | D15: Làm tròn thành số nguyên | E15: Trung bình | F15: XMLComplete_CAN_NANG_CON_THIEU_XML9 | G15: 1 | H15: Kỹ thuật – HIS | I15: CNTT | K15: Không rõ
A16: 12 | B16: XML1 | C16: MA_BENH_CHINH, MA_BENH_KT | D16: Thay chuỗi con 6 mã: U62.152→M15; A91→A90; I84→K64; N18.0→N18; U58.091→I10; U55.561→G51 | E16: Nghiêm trọng | F16: XML1_DISEASE_ICD_CODE_ERROR_MA_BENH_CHINH XML1_DISEASE_ICD_CODE_ERROR_MA_BENH_KT | G16: 6 | H16: Nghiệp vụ – Chuyên môn lâm sàng | I16: Khoa lâm sàng | K16: Không rõ
A17: 13 | B17: XML1 | C17: MA_BENH_CHINH, MA_BENH_KT | D17: Đổi sang mã mới (xem sheet "Ma ICD bi doi") | E17: Nghiêm trọng | F17: XML1_DISEASE_ICD_CODE_ERROR_MA_BENH_CHINH XML1_DISEASE_ICD_CODE_ERROR_MA_BENH_KT | G17: 6 | H17: Nghiệp vụ – Chuyên môn lâm sàng | I17: Khoa lâm sàng | K17: Không dùng
A18: 14 | B18: XML1 | C18: MA_BENH_KT | D18: Loại bỏ khỏi chuỗi bệnh kèm theo (104 mã, xem sheet "Ma Z bi xoa") | E18: Cao | F18: XML1_WARNING_MA_BENH_KT XML1_WARNING_MA_BENH_CHINH | G18: 66 | H18: Nghiệp vụ – Chuyên môn lâm sàng | I18: Khoa lâm sàng | J18: x
A19: 15 | B19: XML1 | C19: MA_DOITUONG_KCB | D19: Suy đoán: tỷ lệ T_TONGCHI_BH/T_TONGCHI_BV ≤ 40% → "3"; khoa K02.1/K02.2 → "2"; còn lại → "1" | E19: Nghiêm trọng | F19: XML1_ADMIN_INFO_ERROR_MA_DOITUONG_KCB XML1_DOI_TUONG_KCB_NGOAI_DANH_MUC | G19: 0 | H19: Nghiệp vụ – Quy định BHYT | I19: Phòng BHYT | K19: Không dùng
A20: 16 | B20: XML1 | C20: PP_DIEU_TRI | D20: Rỗng → "PP_DIEU_TRI" + hằng BSKhongDienTT; dài → cắt 1296 ký tự + "..." | E20: Cao | F20: XML1_SPECIAL_INPATIENT_ERROR_PP_DIEU_TRI | G20: 7 | H20: Nghiệp vụ – Chuyên môn lâm sàng | I20: Khoa lâm sàng | J20: x
A21: 17 | B21: XML1 | C21: GIAY_CHUYEN_TUYEN | D21: Gán số giấy giả "...../20../PCCSKBCB" | E21: Nghiêm trọng | F21: XML1_ADMIN_INFO_ERROR_GIAY_CHUYEN_TUYEN XML1_DOI_TUONG_KCB_THIEU_GIAY_CHUYEN_TUYEN | G21: 8 | H21: Nghiệp vụ – Quy định BHYT | I21: Phòng BHYT | K21: Không dùng
A22: 18 | B22: XML2 | C22: MA_THUOC, TEN_THUOC | D22: Gán hằng BHYTConfig.DuocChuaNhapTT | E22: Cao | F22: XML2_INVALID_DRUG_CODE XML2_MISSING_DRUG_NAME | G22: 396 | H22: Nghiệp vụ – Danh mục | I22: Khoa Dược | K22: Không rõ
A23: 19 | B23: XML2 | C23: MA_THUOC | D23: Đổi thành "9.4.KTNAT" | E23: Cao | F23: XML2_INVALID_DRUG_CODE | G23: 396 | H23: Nghiệp vụ – Danh mục | I23: Khoa Dược | K23: Không rõ
A24: 20 | B24: XML2 | C24: SO_DANG_KY | D24: Gán DuocChuaNhapTT | E24: Trung bình | F24: Chưa có quy tắc tương ứng | K24: Không rõ
A25: 21 | B25: XML2 | C25: NGAY_YL | D25: Kéo NGAY_YL về đúng NGAY_RA / NGAY_VAO | E25: Nghiêm trọng | F25: XML2_INVALID_ORDER_TIME | G25: 1 | H25: Nghiệp vụ – Chuyên môn lâm sàng | I25: Khoa lâm sàng | J25: x
A26: 22 | B26: XML2 | C26: NGAY_TH_YL | D26: Gán NGAY_TH_YL = NGAY_YL | E26: Cao | F26: Chưa có quy tắc tương ứng | J26: x
A27: 23 | B27: XML2 | C27: MA_BAC_SI | D27: Bỏ "CNTT"; rỗng → gán mã CCHN TRƯỞNG KHOA theo MA_KHOA (xem sheet "Truong khoa gan thay") | E27: Nghiêm trọng | F27: XMLComplete_NVYT_THIEU (BS chỉ định XML2) XMLComplete_NVYT_KHONG_CO_TRONG_DM / _SAI_DINH_DANG (BS chỉ định XML2) | G27: 1134 | H27: Nghiệp vụ – Danh mục | I27: Phòng TCCB | J27: x
A28: 24 | B28: XML3 | C28: MA_BENH | D28: Thay chuỗi con 6 mã ICD như XML1 | E28: Nghiêm trọng | F28: XML3_INFO_ERROR_MA_BENH_INVALID | G28: 1 | H28: Nghiệp vụ – Chuyên môn lâm sàng | I28: Khoa lâm sàng | K28: Không dùng
A29: 25 | B29: XML3 | C29: MA_GIUONG | D29: Đổi thành H017 | E29: Cao | F29: XML3_INVALID_BED_CODE_FORMAT | G29: 0 | H29: Nghiệp vụ – Quy định BHYT | I29: Phòng BHYT | K29: Không dùng
A30: 26 | B30: XML3 | C30: MA_VAT_TU, TEN_VAT_TU (nhóm 10) | D30: Gán hằng BHYTConfig.PVTChuaNhapTT | E30: Cao | F30: XML3_MISSING_MATERIAL_CODE XML3_MISSING_MATERIAL_NAME | G30: 0 | H30: Kỹ thuật – HIS | I30: CNTT | K30: Không dùng
A31: 27 | B31: XML3 | C31: GOI_VTYT, MA_DICH_VU, TEN_DICH_VU (nhóm 10) | D31: Xoá cả 3 trường | E31: Nghiêm trọng | F31: Chưa có quy tắc tương ứng | K31: Không rõ
A32: 28 | B32: XML3 | C32: TAI_SU_DUNG (nhóm 10) | D32: Xoá cờ tái sử dụng | E32: Nghiêm trọng | F32: XML3_TAI_SU_DUNG_DON_GIA_LECH | G32: 0 | H32: Kỹ thuật – HIS | I32: CNTT | K32: Không rõ
A33: 29 | B33: XML3 | C33: MA_VAT_TU (DVKT y học hạt nhân) | D33: Gán CỨNG mã "40P.xx" (+ "40P.52") theo từng DVKT – xem sheet "Ma VT gan cung" | E33: Nghiêm trọng | F33: Chưa có quy tắc tương ứng | J33: x
A34: 30 | B34: XML3 | C34: NGAY_YL | D34: Kéo về NGAY_RA / NGAY_VAO | E34: Nghiêm trọng | F34: XML3_INVALID_ORDER_TIME | G34: 2 | H34: Nghiệp vụ – Chuyên môn lâm sàng | I34: Khoa lâm sàng | J34: x
A35: 31 | B35: XML3 | C35: MA_BAC_SI | D35: Bỏ "CNTT"; rỗng → CCHN trưởng khoa | E35: Nghiêm trọng | F35: XMLComplete_NVYT_THIEU (BS chỉ định XML3) XMLComplete_NVYT_KHONG_CO_TRONG_DM / _SAI_DINH_DANG (BS chỉ định XML3) | G35: 1535 | H35: Nghiệp vụ – Danh mục | I35: Phòng TCCB | J35: x
A36: 32 | B36: XML3 | C36: NGAY_KQ | D36: Gán = giờ xuất file − 3 phút, hoặc = NGAY_YL | E36: Cao | F36: XML3_INVALID_NGAY_KQ XML3_NGAY_KQ_GREATER_NGAY_RA XML3_INVALID_NGAY_KQ_LESSTHEN_NGAY_YL | G36: 2031 | H36: Kỹ thuật – Tích hợp HIS–PACS/LIS | I36: CNTT | J36: x
A37: 33 | B37: XML3 | C37: NGAY_TH_YL | D37: Gán = giờ xuất − 3 phút, hoặc = NGAY_YL | E37: Cao | F37: XML3_NGAY_TH_YL_EQUALS_NGAY_KQ XML3_EXECUTION_TIME_UNDER_3MIN | G37: 6758 | H37: Kỹ thuật – HIS | I37: CNTT | J37: x
A38: 34 | B38: XML3 | C38: PP_VO_CAM | D38: Nhóm 8, 18 (PT/TT) → "4"; nhóm khác → rỗng | E38: Nghiêm trọng | F38: XML3_INFO_ERROR_PP_VO_CAM_EMPTY | G38: 75 | H38: Nghiệp vụ – Chuyên môn lâm sàng | I38: Khoa lâm sàng | K38: Không rõ
A39: 35 | B39: XML3 | C39: NGUOI_THUC_HIEN (nhóm 1,2,3,8,18) | D39: Bỏ "CNTT"; DV khí máu 23.0103.1531 hoặc y lệnh trước 01/07/2024 → gán = MA_BAC_SI (người chỉ định); từ 01/07/2024 → "0000000000" | E39: Nghiêm trọng | F39: XMLComplete_NVYT_THIEU (người thực hiện XML3) XMLComplete_NVYT_KHONG_CO_TRONG_DM / _SAI_DINH_DANG (người thực hiện XML3) XML3_SAME_DOCTOR_ORDER_AND_EXECUTE | G39: 10186 | H39: Nghiệp vụ – Danh mục | I39: Phòng TCCB | K39: Không rõ
A40: 36 | B40: XML3 | C40: MA_BENH | D40: Giữ 13 mã đầu, luôn thêm ";" cuối chuỗi | E40: Trung bình | F40: XML3_INFO_ERROR_MA_BENH_TOO_LONG | G40: 0 | H40: Kỹ thuật – HIS | I40: CNTT | K40: Không rõ
A41: 37 | B41: XML4 | C41: GIA_TRI | D41: Cắt 47 ký tự + "..." | E41: Cao | F41: XML4_INFO_ERROR_GIA_TRI_LENGTH | G41: 1091 | H41: Kỹ thuật – Tích hợp HIS–LIS | I41: CNTT | K41: Không rõ
A42: 38 | B42: XML4 | C42: NGAY_KQ | D42: Gán = giờ xuất − 3 phút | E42: Cao | F42: XML4_INFO_ERROR_NGAY_KQ XMLComplete_XML4_NGAY_KQ_MISMATCH_XML3 | G42: 1271 | H42: Kỹ thuật – Tích hợp HIS–PACS/LIS | I42: CNTT | J42: x
A43: 39 | B43: XML4 | C43: MA_BS_DOC_KQ | D43: Lấy MA_BAC_SI (người CHỈ ĐỊNH) của dòng XML3 cùng MA_DICH_VU; không thấy → CCHN trưởng khoa | E43: Nghiêm trọng | F43: XMLComplete_NVYT_THIEU (BS đọc KQ XML4) XMLComplete_NVYT_KHONG_CO_TRONG_DM / _SAI_DINH_DANG (BS đọc KQ XML4) | G43: 10612 | H43: Kỹ thuật – Tích hợp HIS–PACS/LIS | I43: CNTT | J43: x
A44: 40 | B44: XML4 | C44: KET_LUAN | D44: Gán "KET_LUAN" + BSKhongDienTT | E44: Cao | F44: XML4_INFO_ERROR_KET_LUAN_EMPTY | G44: 432 | H44: Kỹ thuật – Tích hợp HIS–PACS | I44: CNTT | K44: Không rõ
A45: 41 | B45: XML5 | C45: THOI_DIEM_DBLS | D45: Gán = giờ xuất − 3 phút | E45: Cao | F45: XML5_INVALID_THOI_DIEM_BDLS | G45: 1 | H45: Nghiệp vụ – Chuyên môn lâm sàng | I45: Khoa lâm sàng | J45: x
A46: 42 | B46: XML5 | C46: NGUOI_THUC_HIEN | D46: Gán CCHN trưởng khoa | E46: Nghiêm trọng | F46: XMLComplete_NVYT_THIEU (người thực hiện XML5) | G46: 0 | H46: Kỹ thuật – HIS | I46: CNTT | J46: x
A47: 43 | B47: XML7 | C47: MA_BS, TEN_BS | D47: Gán mã CCHN + HỌ TÊN trưởng khoa ra viện | E47: Nghiêm trọng | F47: XMLComplete_NVYT_THIEU (BS chỉ định XML7) XMLComplete_NVYT_KHONG_CO_TRONG_DM / _SAI_DINH_DANG (BS chỉ định XML7) | G47: 123 | H47: Nghiệp vụ – Danh mục | I47: Phòng TCCB | K47: Không dùng
A48: 44 | B48: XML7 | C48: PP_DIEUTRI, CHAN_DOAN_RV | D48: Rỗng → tên trường + BSKhongDienTT; dài → cắt 745 + "..." | E48: Cao | F48: XML7_INFO_ERROR_PP_DIEUTRI | G48: 642 | H48: Nghiệp vụ – Chuyên môn lâm sàng | I48: Khoa lâm sàng | J48: x
A49: 45 | B49: XML7 | C49: MA_TTDV | D49: Ghi đè theo cơ sở; BVBM: khác mã cấu hình → CCHN trưởng khoa theo XML1.MA_KHOA | E49: Cao | F49: XMLComplete_NVYT_THIEU (thủ trưởng đơn vị XML7) XMLComplete_NVYT_KHONG_CO_TRONG_DM / _SAI_DINH_DANG (thủ trưởng đơn vị XML7) | G49: 29 | H49: Kỹ thuật – HIS | I49: CNTT | K49: Không dùng
A50: 46 | B50: XML8 | C50: MA_TTDV | D50: Như XML7 | E50: Cao | F50: XMLComplete_NVYT_THIEU (thủ trưởng đơn vị XML8) XMLComplete_NVYT_KHONG_CO_TRONG_DM / _SAI_DINH_DANG (thủ trưởng đơn vị XML8) | G50: 29 | H50: Kỹ thuật – HIS | I50: CNTT | K50: Không dùng
A51: 47 | B51: XML8 | C51: PP_DIEUTRI, QT_BENHLY, TOMTAT_KQ, CHAN_DOAN_RV | D51: Rỗng → tên trường + BSKhongDienTT; QT_BENHLY, TOMTAT_KQ ≥ 1500 → cắt 1296; CHAN_DOAN_RV ≥ 1296 → cắt 1296 | E51: Cao | F51: XML8_INFO_ERROR_PP_DIEUTRI XML8_INFO_ERROR_TOMTAT_KQ XML8_TOMTAT_KQ_TOO_SHORT | G51: 7258 | H51: Nghiệp vụ – Chuyên môn lâm sàng | I51: Khoa lâm sàng | J51: x
A52: 48 | B52: XML8 | C52: KET_QUA_DTRI | D52: Rỗng → "3"; giá trị 1 ký tự ("1" Khỏi, "2" Đỡ, "4" Nặng hơn, "5" Tử vong…) cũng bị ép thành "3" | E52: Nghiêm trọng | F52: XML8_INFO_ERROR_KET_QUA_DTRI | G52: 0 | H52: Nghiệp vụ – Chuyên môn lâm sàng | I52: Khoa lâm sàng | K52: Không dùng
A53: 49 | B53: XML9 | C53: MA_TTDV | D53: Như XML7 | E53: Cao | F53: Chưa có quy tắc tương ứng | K53: Không dùng
A54: 50 | B54: XML9 | C54: CAN_NANG_CON | D54: Gán "3000" (gam) | E54: Nghiêm trọng | F54: Chưa có quy tắc tương ứng | K54: Không rõ
A55: 51 | B55: XML11 | C55: DU_PHONG | D55: Ghi toàn bộ XML của bản ghi vào DU_PHONG | E55: Trung bình | F55: Chưa có quy tắc tương ứng | K55: Không dùng
A56: 52 | B56: XML11 | C56: PP_DIEUTRI | D56: Tên trường + BSKhongDienTT | E56: Cao | F56: XML11_INFO_ERROR_PP_DIEUTRI | G56: 20 | H56: Nghiệp vụ – Chuyên môn lâm sàng | I56: Khoa lâm sàng | J56: x
A57: 53 | B57: XML11 | C57: MA_BS | D57: CCHN trưởng khoa | E57: Nghiêm trọng | F57: XMLComplete_NVYT_KHONG_CO_TRONG_DM / _SAI_DINH_DANG (BS chỉ định XML11) | G57: 3 | H57: Nghiệp vụ – Danh mục | I57: Phòng TCCB | J57: x
A58: 54 | B58: XML13 | C58: MA_BENH_CHINH, MA_BENH_KT | D58: Như XML1 (6 mã + bảng 27 mã + lọc Z) | E58: Nghiêm trọng | F58: XML13_INFO_ERROR_MA_BENH_CHINH_NOT_FOUND XML13_INFO_ERROR_MA_BENH_KT_NOT_FOUND | G58: 2 | H58: Nghiệp vụ – Chuyên môn lâm sàng | I58: Khoa lâm sàng | K58: Không dùng
A59: 55 | B59: XML13 | C59: MA_TTDV | D59: Như XML7 | E59: Cao | F59: XMLComplete_NVYT_THIEU (thủ trưởng đơn vị XML13) XMLComplete_NVYT_KHONG_CO_TRONG_DM / _SAI_DINH_DANG (thủ trưởng đơn vị XML13) | G59: 9 | H59: Nghiệp vụ – Danh mục | I59: Phòng TCCB | K59: Không dùng
A60: 56 | B60: XML13 | C60: TOMTAT_KQ, QT_BENHLY, DAU_HIEU_LS | D60: Rỗng → tên trường + BSKhongDienTT; dài → cắt 2997 + "..." | E60: Cao | F60: XML13_INFO_ERROR_TOMTAT_KQ XML13_INFO_ERROR_QT_BENHLY XML13_INFO_ERROR_DAU_HIEU_LS | G60: 0 | H60: Nghiệp vụ – Chuyên môn lâm sàng | I60: Khoa lâm sàng | J60: x
A61: 57 | B61: XML14 | C61: MA_BENH_CHINH, MA_BENH_KT | D61: Như XML1 | E61: Nghiêm trọng | F61: Chưa có quy tắc tương ứng | K61: Không dùng
A62: 58 | B62: XML14 | C62: MA_TTDV | D62: Như XML7 | E62: Cao | F62: XMLComplete_NVYT_THIEU (thủ trưởng đơn vị XML14) XMLComplete_NVYT_KHONG_CO_TRONG_DM / _SAI_DINH_DANG (thủ trưởng đơn vị XML14) | G62: 323 | H62: Kỹ thuật – HIS | I62: CNTT | K62: Không dùng
A63: 59 | B63: XML14 | C63: NGAY_HEN_KL | D63: Cộng thêm 1 ngày | E63: Nghiêm trọng | F63: XML14_INFO_ERROR_NGAY_HEN_KL_SMALLER_NGAY_RA | G63: 362 | H63: Nghiệp vụ – Chuyên môn lâm sàng | I63: Khoa lâm sàng | J63: x

Sheet Ghi chú
A1: CÁCH ĐỌC VÀ PHÂN LOẠI
A2: • Nguồn số liệu: chạy lại bộ kiểm hiện tại (commit 63e21fa8) ở chế độ chỉ đọc trên CSDL thật ngày 16/10/2026 cho 23.967 hồ sơ BHYT ra viện 01/10–15/10/2026 (nạp lại ngày 16/10/2026) (0 hồ sơ lỗi chạy; nhóm này không có hồ sơ viện phí MA_DOITUONG_KCB = 9); mã lỗi đang tắt kiểm (is_check = 0) bị loại như khi ghi thật. Cột P sheet "Danh mục lỗi" = cùng nhóm hồ sơ khi kiểm sáng 16/10, trước khi nạp lại.
A3: • Đối chiếu: kết quả chạy lại khớp kết quả hệ thống đã ghi khi nạp (157.141 so với 157.205 cặp hồ sơ–mã lỗi; chênh lệch nhỏ do vài hồ sơ kiểm trước khi bản cập nhật quy tắc mới nhất có hiệu lực). Số trong tệp vì vậy cũng là số các đơn vị đang thấy trên màn hình Tiền giám định.
A4: • "Chặn gửi" = lỗi xuất toán (critical): hồ sơ không được xuất, ký, gửi cổng. "Không" = cảnh báo, vẫn gửi nhưng có nguy cơ bị BHXH giảm trừ.
A5: • Nhóm lớn: Nghiệp vụ = lỗi do người nhập/quy trình/danh mục; Kỹ thuật = lỗi do HIS, kết nối PACS/LIS/thiết bị, hoặc phần mềm kiểm.
A6: • Danh mục được xếp vào Nghiệp vụ vì đơn vị chủ quản danh mục (Dược, VT-TBYT, KHTH, TCKT, TCCB) phải sửa; CNTT chỉ phối hợp nạp.
A7: • Một lỗi có thể có nhiều nguyên nhân; bảng ghi nguyên nhân chính quan sát được trên dữ liệu thật, đơn vị phối hợp ghi ở cột riêng.
A8: • Thay đổi quy tắc từ bản 14/10: gộp 34 mã NVYT thành 3 mã XMLComplete_NVYT_* (thiếu / không có trong DM / sai định dạng); gộp mã + tên chỉ số trống thành XML4_CHI_SO_EMPTY; thiếu mã máy căn cứ danh mục DVKT cần mã máy (bỏ lọc theo nhóm 1/2/3); thêm quy tắc vật phẩm kèm DVKT, thời gian thực hiện dài bất thường; bỏ báo trùng giữa quy tắc cũ và mới; tắt kiểm một số mã (vd. XML2_INVALID_DON_VI_TINH). Vì kiểm lại toàn bộ nên số liệu có thể TĂNG ở mã có quy tắc mới/mở rộng.
A9: • Cột FIXERROR: số quy tắc trong tệp phân tích hệ thống khác – nơi lỗi đó bị tự sửa trên bản gửi cổng thay vì sửa tại nguồn.
A10: • Dòng chữ xám = mã lỗi chưa phát sinh trong kỳ.
